{
 "build_id": "2.3",
 "data": [
  {
   "label": "Overall",
   "data": [
    {
     "policy": "C1_School closing",
     "score": 73,
     "rank": 9
    },
    {
     "policy": "C2_Workplace closing",
     "score": 56,
     "rank": 11
    },
    {
     "policy": "C3_Cancel public events",
     "score": 90,
     "rank": 7
    },
    {
     "policy": "C4_Restrictions on gatherings",
     "score": 90,
     "rank": 1
    },
    {
     "policy": "C5_Close public transport",
     "score": 26,
     "rank": 14
    },
    {
     "policy": "C6_Stay at home requirements",
     "score": 28,
     "rank": 15
    },
    {
     "policy": "C7_Restrictions on internal movement",
     "score": 24,
     "rank": 8
    },
    {
     "policy": "C8_International travel controls",
     "score": 82,
     "rank": 2
    },
    {
     "policy": "E1_Income support",
     "score": 72,
     "rank": 13
    },
    {
     "policy": "E2_Debt_contract relief",
     "score": 98,
     "rank": 6
    },
    {
     "policy": "H1_Public information campaigns",
     "score": 100,
     "rank": 10
    },
    {
     "policy": "H2_Testing policy",
     "score": 89,
     "rank": 3
    },
    {
     "policy": "H3_Contact tracing",
     "score": 100,
     "rank": 12
    },
    {
     "policy": "H6_Facial Coverings",
     "score": 44,
     "rank": 5
    },
    {
     "policy": "H7_Vaccination policy",
     "score": 62,
     "rank": 4
    }
   ]
  },
  {
   "label": "Month 1",
   "data": [
    {
     "policy": "C1_School closing",
     "score": 100,
     "rank": 9
    },
    {
     "policy": "C2_Workplace closing",
     "score": 46,
     "rank": 11
    },
    {
     "policy": "C3_Cancel public events",
     "score": 100,
     "rank": 7
    },
    {
     "policy": "C4_Restrictions on gatherings",
     "score": 0,
     "rank": 1
    },
    {
     "policy": "C5_Close public transport",
     "score": 0,
     "rank": 14
    },
    {
     "policy": "C6_Stay at home requirements",
     "score": 33,
     "rank": 15
    },
    {
     "policy": "C7_Restrictions on internal movement",
     "score": 0,
     "rank": 8
    },
    {
     "policy": "C8_International travel controls",
     "score": 75,
     "rank": 2
    },
    {
     "policy": "E1_Income support",
     "score": 76,
     "rank": 13
    },
    {
     "policy": "E2_Debt_contract relief",
     "score": 76,
     "rank": 6
    },
    {
     "policy": "H1_Public information campaigns",
     "score": 100,
     "rank": 10
    },
    {
     "policy": "H2_Testing policy",
     "score": 66,
     "rank": 3
    },
    {
     "policy": "H3_Contact tracing",
     "score": 100,
     "rank": 12
    },
    {
     "policy": "H6_Facial Coverings",
     "score": 25,
     "rank": 5
    },
    {
     "policy": "H7_Vaccination policy",
     "score": 12,
     "rank": 4
    }
   ]
  },
  {
   "label": "Month 2",
   "data": [
    {
     "policy": "C1_School closing",
     "score": 100,
     "rank": 9
    },
    {
     "policy": "C2_Workplace closing",
     "score": 63,
     "rank": 11
    },
    {
     "policy": "C3_Cancel public events",
     "score": 100,
     "rank": 7
    },
    {
     "policy": "C4_Restrictions on gatherings",
     "score": 70,
     "rank": 1
    },
    {
     "policy": "C5_Close public transport",
     "score": 0,
     "rank": 14
    },
    {
     "policy": "C6_Stay at home requirements",
     "score": 33,
     "rank": 15
    },
    {
     "policy": "C7_Restrictions on internal movement",
     "score": 0,
     "rank": 8
    },
    {
     "policy": "C8_International travel controls",
     "score": 85,
     "rank": 2
    },
    {
     "policy": "E1_Income support",
     "score": 100,
     "rank": 13
    },
    {
     "policy": "E2_Debt_contract relief",
     "score": 100,
     "rank": 6
    },
    {
     "policy": "H1_Public information campaigns",
     "score": 100,
     "rank": 10
    },
    {
     "policy": "H2_Testing policy",
     "score": 66,
     "rank": 3
    },
    {
     "policy": "H3_Contact tracing",
     "score": 100,
     "rank": 12
    },
    {
     "policy": "H6_Facial Coverings",
     "score": 25,
     "rank": 5
    },
    {
     "policy": "H7_Vaccination policy",
     "score": 20,
     "rank": 4
    }
   ]
  },
  {
   "label": "Month 3",
   "data": [
    {
     "policy": "C1_School closing",
     "score": 100,
     "rank": 9
    },
    {
     "policy": "C2_Workplace closing",
     "score": 66,
     "rank": 11
    },
    {
     "policy": "C3_Cancel public events",
     "score": 100,
     "rank": 7
    },
    {
     "policy": "C4_Restrictions on gatherings",
     "score": 90,
     "rank": 1
    },
    {
     "policy": "C5_Close public transport",
     "score": 0,
     "rank": 14
    },
    {
     "policy": "C6_Stay at home requirements",
     "score": 33,
     "rank": 15
    },
    {
     "policy": "C7_Restrictions on internal movement",
     "score": 0,
     "rank": 8
    },
    {
     "policy": "C8_International travel controls",
     "score": 100,
     "rank": 2
    },
    {
     "policy": "E1_Income support",
     "score": 100,
     "rank": 13
    },
    {
     "policy": "E2_Debt_contract relief",
     "score": 100,
     "rank": 6
    },
    {
     "policy": "H1_Public information campaigns",
     "score": 100,
     "rank": 10
    },
    {
     "policy": "H2_Testing policy",
     "score": 66,
     "rank": 3
    },
    {
     "policy": "H3_Contact tracing",
     "score": 100,
     "rank": 12
    },
    {
     "policy": "H6_Facial Coverings",
     "score": 25,
     "rank": 5
    },
    {
     "policy": "H7_Vaccination policy",
     "score": 29,
     "rank": 4
    }
   ]
  },
  {
   "label": "Month 4",
   "data": [
    {
     "policy": "C1_School closing",
     "score": 75,
     "rank": 9
    },
    {
     "policy": "C2_Workplace closing",
     "score": 22,
     "rank": 11
    },
    {
     "policy": "C3_Cancel public events",
     "score": 100,
     "rank": 7
    },
    {
     "policy": "C4_Restrictions on gatherings",
     "score": 75,
     "rank": 1
    },
    {
     "policy": "C5_Close public transport",
     "score": 0,
     "rank": 14
    },
    {
     "policy": "C6_Stay at home requirements",
     "score": 33,
     "rank": 15
    },
    {
     "policy": "C7_Restrictions on internal movement",
     "score": 0,
     "rank": 8
    },
    {
     "policy": "C8_International travel controls",
     "score": 100,
     "rank": 2
    },
    {
     "policy": "E1_Income support",
     "score": 100,
     "rank": 13
    },
    {
     "policy": "E2_Debt_contract relief",
     "score": 100,
     "rank": 6
    },
    {
     "policy": "H1_Public information campaigns",
     "score": 100,
     "rank": 10
    },
    {
     "policy": "H2_Testing policy",
     "score": 66,
     "rank": 3
    },
    {
     "policy": "H3_Contact tracing",
     "score": 100,
     "rank": 12
    },
    {
     "policy": "H6_Facial Coverings",
     "score": 25,
     "rank": 5
    },
    {
     "policy": "H7_Vaccination policy",
     "score": 37,
     "rank": 4
    }
   ]
  },
  {
   "label": "Month 5",
   "data": [
    {
     "policy": "C1_School closing",
     "score": 70,
     "rank": 9
    },
    {
     "policy": "C2_Workplace closing",
     "score": 6,
     "rank": 11
    },
    {
     "policy": "C3_Cancel public events",
     "score": 13,
     "rank": 7
    },
    {
     "policy": "C4_Restrictions on gatherings",
     "score": 77,
     "rank": 1
    },
    {
     "policy": "C5_Close public transport",
     "score": 0,
     "rank": 14
    },
    {
     "policy": "C6_Stay at home requirements",
     "score": 33,
     "rank": 15
    },
    {
     "policy": "C7_Restrictions on internal movement",
     "score": 0,
     "rank": 8
    },
    {
     "policy": "C8_International travel controls",
     "score": 100,
     "rank": 2
    },
    {
     "policy": "E1_Income support",
     "score": 100,
     "rank": 13
    },
    {
     "policy": "E2_Debt_contract relief",
     "score": 100,
     "rank": 6
    },
    {
     "policy": "H1_Public information campaigns",
     "score": 100,
     "rank": 10
    },
    {
     "policy": "H2_Testing policy",
     "score": 66,
     "rank": 3
    },
    {
     "policy": "H3_Contact tracing",
     "score": 100,
     "rank": 12
    },
    {
     "policy": "H6_Facial Coverings",
     "score": 25,
     "rank": 5
    },
    {
     "policy": "H7_Vaccination policy",
     "score": 48,
     "rank": 4
    }
   ]
  },
  {
   "label": "Month 6",
   "data": [
    {
     "policy": "C1_School closing",
     "score": 100,
     "rank": 9
    },
    {
     "policy": "C2_Workplace closing",
     "score": 66,
     "rank": 11
    },
    {
     "policy": "C3_Cancel public events",
     "score": 100,
     "rank": 7
    },
    {
     "policy": "C4_Restrictions on gatherings",
     "score": 100,
     "rank": 1
    },
    {
     "policy": "C5_Close public transport",
     "score": 0,
     "rank": 14
    },
    {
     "policy": "C6_Stay at home requirements",
     "score": 33,
     "rank": 15
    },
    {
     "policy": "C7_Restrictions on internal movement",
     "score": 0,
     "rank": 8
    },
    {
     "policy": "C8_International travel controls",
     "score": 100,
     "rank": 2
    },
    {
     "policy": "E1_Income support",
     "score": 100,
     "rank": 13
    },
    {
     "policy": "E2_Debt_contract relief",
     "score": 100,
     "rank": 6
    },
    {
     "policy": "H1_Public information campaigns",
     "score": 100,
     "rank": 10
    },
    {
     "policy": "H2_Testing policy",
     "score": 77,
     "rank": 3
    },
    {
     "policy": "H3_Contact tracing",
     "score": 100,
     "rank": 12
    },
    {
     "policy": "H6_Facial Coverings",
     "score": 56,
     "rank": 5
    },
    {
     "policy": "H7_Vaccination policy",
     "score": 60,
     "rank": 4
    }
   ]
  },
  {
   "label": "Month 7",
   "data": [
    {
     "policy": "C1_School closing",
     "score": 100,
     "rank": 9
    },
    {
     "policy": "C2_Workplace closing",
     "score": 66,
     "rank": 11
    },
    {
     "policy": "C3_Cancel public events",
     "score": 100,
     "rank": 7
    },
    {
     "policy": "C4_Restrictions on gatherings",
     "score": 100,
     "rank": 1
    },
    {
     "policy": "C5_Close public transport",
     "score": 0,
     "rank": 14
    },
    {
     "policy": "C6_Stay at home requirements",
     "score": 27,
     "rank": 15
    },
    {
     "policy": "C7_Restrictions on internal movement",
     "score": 0,
     "rank": 8
    },
    {
     "policy": "C8_International travel controls",
     "score": 100,
     "rank": 2
    },
    {
     "policy": "E1_Income support",
     "score": 100,
     "rank": 13
    },
    {
     "policy": "E2_Debt_contract relief",
     "score": 100,
     "rank": 6
    },
    {
     "policy": "H1_Public information campaigns",
     "score": 100,
     "rank": 10
    },
    {
     "policy": "H2_Testing policy",
     "score": 100,
     "rank": 3
    },
    {
     "policy": "H3_Contact tracing",
     "score": 100,
     "rank": 12
    },
    {
     "policy": "H6_Facial Coverings",
     "score": 70,
     "rank": 5
    }
   ]
  },
  {
   "label": "Month 8",
   "data": [
    {
     "policy": "C1_School closing",
     "score": 55,
     "rank": 9
    },
    {
     "policy": "C2_Workplace closing",
     "score": 44,
     "rank": 11
    },
    {
     "policy": "C3_Cancel public events",
     "score": 100,
     "rank": 7
    },
    {
     "policy": "C4_Restrictions on gatherings",
     "score": 100,
     "rank": 1
    },
    {
     "policy": "C5_Close public transport",
     "score": 0,
     "rank": 14
    },
    {
     "policy": "C6_Stay at home requirements",
     "score": 0,
     "rank": 15
    },
    {
     "policy": "C7_Restrictions on internal movement",
     "score": 0,
     "rank": 8
    },
    {
     "policy": "C8_International travel controls",
     "score": 100,
     "rank": 2
    },
    {
     "policy": "E1_Income support",
     "score": 100,
     "rank": 13
    },
    {
     "policy": "E2_Debt_contract relief",
     "score": 100,
     "rank": 6
    },
    {
     "policy": "H1_Public information campaigns",
     "score": 100,
     "rank": 10
    },
    {
     "policy": "H2_Testing policy",
     "score": 100,
     "rank": 3
    },
    {
     "policy": "H3_Contact tracing",
     "score": 100,
     "rank": 12
    },
    {
     "policy": "H6_Facial Coverings",
     "score": 50,
     "rank": 5
    }
   ]
  },
  {
   "label": "Month 9",
   "data": [
    {
     "policy": "C1_School closing",
     "score": 34,
     "rank": 9
    },
    {
     "policy": "C2_Workplace closing",
     "score": 33,
     "rank": 11
    },
    {
     "policy": "C3_Cancel public events",
     "score": 100,
     "rank": 7
    },
    {
     "policy": "C4_Restrictions on gatherings",
     "score": 100,
     "rank": 1
    },
    {
     "policy": "C5_Close public transport",
     "score": 8,
     "rank": 14
    },
    {
     "policy": "C6_Stay at home requirements",
     "score": 0,
     "rank": 15
    },
    {
     "policy": "C7_Restrictions on internal movement",
     "score": 0,
     "rank": 8
    },
    {
     "policy": "C8_International travel controls",
     "score": 91,
     "rank": 2
    },
    {
     "policy": "E1_Income support",
     "score": 91,
     "rank": 13
    },
    {
     "policy": "E2_Debt_contract relief",
     "score": 100,
     "rank": 6
    },
    {
     "policy": "H1_Public information campaigns",
     "score": 100,
     "rank": 10
    },
    {
     "policy": "H2_Testing policy",
     "score": 100,
     "rank": 3
    },
    {
     "policy": "H3_Contact tracing",
     "score": 100,
     "rank": 12
    },
    {
     "policy": "H6_Facial Coverings",
     "score": 50,
     "rank": 5
    }
   ]
  },
  {
   "label": "Month 10",
   "data": [
    {
     "policy": "C1_School closing",
     "score": 66,
     "rank": 9
    },
    {
     "policy": "C2_Workplace closing",
     "score": 56,
     "rank": 11
    },
    {
     "policy": "C3_Cancel public events",
     "score": 100,
     "rank": 7
    },
    {
     "policy": "C4_Restrictions on gatherings",
     "score": 100,
     "rank": 1
    },
    {
     "policy": "C5_Close public transport",
     "score": 50,
     "rank": 14
    },
    {
     "policy": "C6_Stay at home requirements",
     "score": 16,
     "rank": 15
    },
    {
     "policy": "C7_Restrictions on internal movement",
     "score": 25,
     "rank": 8
    },
    {
     "policy": "C8_International travel controls",
     "score": 59,
     "rank": 2
    },
    {
     "policy": "E1_Income support",
     "score": 50,
     "rank": 13
    },
    {
     "policy": "E2_Debt_contract relief",
     "score": 100,
     "rank": 6
    },
    {
     "policy": "H1_Public information campaigns",
     "score": 100,
     "rank": 10
    },
    {
     "policy": "H2_Testing policy",
     "score": 100,
     "rank": 3
    },
    {
     "policy": "H3_Contact tracing",
     "score": 100,
     "rank": 12
    },
    {
     "policy": "H6_Facial Coverings",
     "score": 50,
     "rank": 5
    }
   ]
  },
  {
   "label": "Month 11",
   "data": [
    {
     "policy": "C1_School closing",
     "score": 66,
     "rank": 9
    },
    {
     "policy": "C2_Workplace closing",
     "score": 66,
     "rank": 11
    },
    {
     "policy": "C3_Cancel public events",
     "score": 100,
     "rank": 7
    },
    {
     "policy": "C4_Restrictions on gatherings",
     "score": 100,
     "rank": 1
    },
    {
     "policy": "C5_Close public transport",
     "score": 50,
     "rank": 14
    },
    {
     "policy": "C6_Stay at home requirements",
     "score": 33,
     "rank": 15
    },
    {
     "policy": "C7_Restrictions on internal movement",
     "score": 50,
     "rank": 8
    },
    {
     "policy": "C8_International travel controls",
     "score": 75,
     "rank": 2
    },
    {
     "policy": "E1_Income support",
     "score": 50,
     "rank": 13
    },
    {
     "policy": "E2_Debt_contract relief",
     "score": 100,
     "rank": 6
    },
    {
     "policy": "H1_Public information campaigns",
     "score": 100,
     "rank": 10
    },
    {
     "policy": "H2_Testing policy",
     "score": 100,
     "rank": 3
    },
    {
     "policy": "H3_Contact tracing",
     "score": 100,
     "rank": 12
    },
    {
     "policy": "H6_Facial Coverings",
     "score": 50,
     "rank": 5
    }
   ]
  },
  {
   "label": "Month 12",
   "data": [
    {
     "policy": "C1_School closing",
     "score": 66,
     "rank": 9
    },
    {
     "policy": "C2_Workplace closing",
     "score": 66,
     "rank": 11
    },
    {
     "policy": "C3_Cancel public events",
     "score": 100,
     "rank": 7
    },
    {
     "policy": "C4_Restrictions on gatherings",
     "score": 100,
     "rank": 1
    },
    {
     "policy": "C5_Close public transport",
     "score": 50,
     "rank": 14
    },
    {
     "policy": "C6_Stay at home requirements",
     "score": 33,
     "rank": 15
    },
    {
     "policy": "C7_Restrictions on internal movement",
     "score": 50,
     "rank": 8
    },
    {
     "policy": "C8_International travel controls",
     "score": 75,
     "rank": 2
    },
    {
     "policy": "E1_Income support",
     "score": 50,
     "rank": 13
    },
    {
     "policy": "E2_Debt_contract relief",
     "score": 100,
     "rank": 6
    },
    {
     "policy": "H1_Public information campaigns",
     "score": 100,
     "rank": 10
    },
    {
     "policy": "H2_Testing policy",
     "score": 100,
     "rank": 3
    },
    {
     "policy": "H3_Contact tracing",
     "score": 100,
     "rank": 12
    },
    {
     "policy": "H6_Facial Coverings",
     "score": 50,
     "rank": 5
    }
   ]
  },
  {
   "label": "Month 13",
   "data": [
    {
     "policy": "C1_School closing",
     "score": 66,
     "rank": 9
    },
    {
     "policy": "C2_Workplace closing",
     "score": 66,
     "rank": 11
    },
    {
     "policy": "C3_Cancel public events",
     "score": 100,
     "rank": 7
    },
    {
     "policy": "C4_Restrictions on gatherings",
     "score": 100,
     "rank": 1
    },
    {
     "policy": "C5_Close public transport",
     "score": 50,
     "rank": 14
    },
    {
     "policy": "C6_Stay at home requirements",
     "score": 33,
     "rank": 15
    },
    {
     "policy": "C7_Restrictions on internal movement",
     "score": 50,
     "rank": 8
    },
    {
     "policy": "C8_International travel controls",
     "score": 75,
     "rank": 2
    },
    {
     "policy": "E1_Income support",
     "score": 50,
     "rank": 13
    },
    {
     "policy": "E2_Debt_contract relief",
     "score": 100,
     "rank": 6
    },
    {
     "policy": "H1_Public information campaigns",
     "score": 100,
     "rank": 10
    },
    {
     "policy": "H2_Testing policy",
     "score": 100,
     "rank": 3
    },
    {
     "policy": "H3_Contact tracing",
     "score": 100,
     "rank": 12
    },
    {
     "policy": "H6_Facial Coverings",
     "score": 50,
     "rank": 5
    }
   ]
  },
  {
   "label": "Month 14",
   "data": [
    {
     "policy": "C1_School closing",
     "score": 66,
     "rank": 9
    },
    {
     "policy": "C2_Workplace closing",
     "score": 66,
     "rank": 11
    },
    {
     "policy": "C3_Cancel public events",
     "score": 100,
     "rank": 7
    },
    {
     "policy": "C4_Restrictions on gatherings",
     "score": 100,
     "rank": 1
    },
    {
     "policy": "C5_Close public transport",
     "score": 50,
     "rank": 14
    },
    {
     "policy": "C6_Stay at home requirements",
     "score": 33,
     "rank": 15
    },
    {
     "policy": "C7_Restrictions on internal movement",
     "score": 50,
     "rank": 8
    },
    {
     "policy": "C8_International travel controls",
     "score": 75,
     "rank": 2
    },
    {
     "policy": "E1_Income support",
     "score": 50,
     "rank": 13
    },
    {
     "policy": "E2_Debt_contract relief",
     "score": 100,
     "rank": 6
    },
    {
     "policy": "H1_Public information campaigns",
     "score": 100,
     "rank": 10
    },
    {
     "policy": "H2_Testing policy",
     "score": 100,
     "rank": 3
    },
    {
     "policy": "H3_Contact tracing",
     "score": 100,
     "rank": 12
    },
    {
     "policy": "H6_Facial Coverings",
     "score": 50,
     "rank": 5
    }
   ]
  },
  {
   "label": "Month 15",
   "data": [
    {
     "policy": "C1_School closing",
     "score": 66,
     "rank": 9
    },
    {
     "policy": "C2_Workplace closing",
     "score": 66,
     "rank": 11
    },
    {
     "policy": "C3_Cancel public events",
     "score": 100,
     "rank": 7
    },
    {
     "policy": "C4_Restrictions on gatherings",
     "score": 100,
     "rank": 1
    },
    {
     "policy": "C5_Close public transport",
     "score": 50,
     "rank": 14
    },
    {
     "policy": "C6_Stay at home requirements",
     "score": 33,
     "rank": 15
    },
    {
     "policy": "C7_Restrictions on internal movement",
     "score": 50,
     "rank": 8
    },
    {
     "policy": "C8_International travel controls",
     "score": 75,
     "rank": 2
    },
    {
     "policy": "E1_Income support",
     "score": 50,
     "rank": 13
    },
    {
     "policy": "E2_Debt_contract relief",
     "score": 100,
     "rank": 6
    },
    {
     "policy": "H1_Public information campaigns",
     "score": 100,
     "rank": 10
    },
    {
     "policy": "H2_Testing policy",
     "score": 100,
     "rank": 3
    },
    {
     "policy": "H3_Contact tracing",
     "score": 100,
     "rank": 12
    },
    {
     "policy": "H6_Facial Coverings",
     "score": 50,
     "rank": 5
    }
   ]
  },
  {
   "label": "Month 16",
   "data": [
    {
     "policy": "C1_School closing",
     "score": 66,
     "rank": 9
    },
    {
     "policy": "C2_Workplace closing",
     "score": 66,
     "rank": 11
    },
    {
     "policy": "C3_Cancel public events",
     "score": 100,
     "rank": 7
    },
    {
     "policy": "C4_Restrictions on gatherings",
     "score": 100,
     "rank": 1
    },
    {
     "policy": "C5_Close public transport",
     "score": 50,
     "rank": 14
    },
    {
     "policy": "C6_Stay at home requirements",
     "score": 33,
     "rank": 15
    },
    {
     "policy": "C7_Restrictions on internal movement",
     "score": 50,
     "rank": 8
    },
    {
     "policy": "C8_International travel controls",
     "score": 75,
     "rank": 2
    },
    {
     "policy": "E1_Income support",
     "score": 50,
     "rank": 13
    },
    {
     "policy": "E2_Debt_contract relief",
     "score": 100,
     "rank": 6
    },
    {
     "policy": "H1_Public information campaigns",
     "score": 100,
     "rank": 10
    },
    {
     "policy": "H2_Testing policy",
     "score": 100,
     "rank": 3
    },
    {
     "policy": "H3_Contact tracing",
     "score": 100,
     "rank": 12
    },
    {
     "policy": "H6_Facial Coverings",
     "score": 50,
     "rank": 5
    }
   ]
  },
  {
   "label": "Month 17",
   "data": [
    {
     "policy": "C1_School closing",
     "score": 66,
     "rank": 9
    },
    {
     "policy": "C2_Workplace closing",
     "score": 66,
     "rank": 11
    },
    {
     "policy": "C3_Cancel public events",
     "score": 91,
     "rank": 7
    },
    {
     "policy": "C4_Restrictions on gatherings",
     "score": 100,
     "rank": 1
    },
    {
     "policy": "C5_Close public transport",
     "score": 50,
     "rank": 14
    },
    {
     "policy": "C6_Stay at home requirements",
     "score": 33,
     "rank": 15
    },
    {
     "policy": "C7_Restrictions on internal movement",
     "score": 50,
     "rank": 8
    },
    {
     "policy": "C8_International travel controls",
     "score": 75,
     "rank": 2
    },
    {
     "policy": "E1_Income support",
     "score": 50,
     "rank": 13
    },
    {
     "policy": "E2_Debt_contract relief",
     "score": 100,
     "rank": 6
    },
    {
     "policy": "H1_Public information campaigns",
     "score": 100,
     "rank": 10
    },
    {
     "policy": "H2_Testing policy",
     "score": 100,
     "rank": 3
    },
    {
     "policy": "H3_Contact tracing",
     "score": 100,
     "rank": 12
    },
    {
     "policy": "H6_Facial Coverings",
     "score": 50,
     "rank": 5
    }
   ]
  },
  {
   "label": "Month 18",
   "data": [
    {
     "policy": "C1_School closing",
     "score": 66,
     "rank": 9
    },
    {
     "policy": "C2_Workplace closing",
     "score": 66,
     "rank": 11
    },
    {
     "policy": "C3_Cancel public events",
     "score": 50,
     "rank": 7
    },
    {
     "policy": "C4_Restrictions on gatherings",
     "score": 100,
     "rank": 1
    },
    {
     "policy": "C5_Close public transport",
     "score": 50,
     "rank": 14
    },
    {
     "policy": "C6_Stay at home requirements",
     "score": 33,
     "rank": 15
    },
    {
     "policy": "C7_Restrictions on internal movement",
     "score": 50,
     "rank": 8
    },
    {
     "policy": "C8_International travel controls",
     "score": 72,
     "rank": 2
    },
    {
     "policy": "E1_Income support",
     "score": 50,
     "rank": 13
    },
    {
     "policy": "E2_Debt_contract relief",
     "score": 100,
     "rank": 6
    },
    {
     "policy": "H1_Public information campaigns",
     "score": 100,
     "rank": 10
    },
    {
     "policy": "H2_Testing policy",
     "score": 100,
     "rank": 3
    },
    {
     "policy": "H3_Contact tracing",
     "score": 100,
     "rank": 12
    },
    {
     "policy": "H6_Facial Coverings",
     "score": 50,
     "rank": 5
    }
   ]
  }
 ]
}