{
 "build_id": "2.3",
 "data": [
  {
   "label": "Overall",
   "data": [
    {
     "iso": "AFG",
     "score": 6,
     "rank": 6
    },
    {
     "iso": "AGO",
     "score": 12,
     "rank": 9
    },
    {
     "iso": "ALB",
     "score": 29,
     "rank": 4
    },
    {
     "iso": "AND",
     "score": 64,
     "rank": 2
    },
    {
     "iso": "ARE",
     "score": 97,
     "rank": 1
    },
    {
     "iso": "ARG",
     "score": 51,
     "rank": 4
    },
    {
     "iso": "AUS",
     "score": 49,
     "rank": 14
    },
    {
     "iso": "AUT",
     "score": 62,
     "rank": 2
    },
    {
     "iso": "AZE",
     "score": 44,
     "rank": 3
    },
    {
     "iso": "BEL",
     "score": 72,
     "rank": 1
    },
    {
     "iso": "BEN",
     "score": 12,
     "rank": 7
    },
    {
     "iso": "BFA",
     "score": 0,
     "rank": 15
    },
    {
     "iso": "BGD",
     "score": 13,
     "rank": 10
    },
    {
     "iso": "BGR",
     "score": 29,
     "rank": 8
    },
    {
     "iso": "BHR",
     "score": 0,
     "rank": 11
    },
    {
     "iso": "BHS",
     "score": 31,
     "rank": 5
    },
    {
     "iso": "BIH",
     "score": 18,
     "rank": 5
    },
    {
     "iso": "BLR",
     "score": 17,
     "rank": 7
    },
    {
     "iso": "BLZ",
     "score": 35,
     "rank": 11
    },
    {
     "iso": "BOL",
     "score": 30,
     "rank": 4
    },
    {
     "iso": "BRA",
     "score": 53,
     "rank": 2
    },
    {
     "iso": "BRB",
     "score": 44,
     "rank": 3
    },
    {
     "iso": "BRN",
     "score": 48,
     "rank": 3
    },
    {
     "iso": "BTN",
     "score": 73,
     "rank": 1
    },
    {
     "iso": "BWA",
     "score": 13,
     "rank": 8
    },
    {
     "iso": "CAF",
     "score": 6,
     "rank": 15
    },
    {
     "iso": "CAN",
     "score": 74,
     "rank": 1
    },
    {
     "iso": "CHE",
     "score": 59,
     "rank": 1
    },
    {
     "iso": "CHL",
     "score": 78,
     "rank": 1
    },
    {
     "iso": "CHN",
     "score": 74,
     "rank": 3
    },
    {
     "iso": "CIV",
     "score": 17,
     "rank": 6
    },
    {
     "iso": "CMR",
     "score": 0,
     "rank": 15
    },
    {
     "iso": "COD",
     "score": 0,
     "rank": 8
    },
    {
     "iso": "COL",
     "score": 40,
     "rank": 14
    },
    {
     "iso": "COM",
     "score": 0,
     "rank": 2
    },
    {
     "iso": "CPV",
     "score": 35,
     "rank": 8
    },
    {
     "iso": "CRI",
     "score": 50,
     "rank": 2
    },
    {
     "iso": "CUB",
     "score": 78,
     "rank": 1
    },
    {
     "iso": "CYP",
     "score": 59,
     "rank": 1
    },
    {
     "iso": "CZE",
     "score": 58,
     "rank": 2
    },
    {
     "iso": "DEU",
     "score": 65,
     "rank": 2
    },
    {
     "iso": "DJI",
     "score": 11,
     "rank": 10
    },
    {
     "iso": "DMA",
     "score": 42,
     "rank": 2
    },
    {
     "iso": "DNK",
     "score": 76,
     "rank": 1
    },
    {
     "iso": "DOM",
     "score": 57,
     "rank": 1
    },
    {
     "iso": "DZA",
     "score": 14,
     "rank": 9
    },
    {
     "iso": "ECU",
     "score": 58,
     "rank": 1
    },
    {
     "iso": "EGY",
     "score": 12,
     "rank": 15
    },
    {
     "iso": "ESP",
     "score": 72,
     "rank": 1
    },
    {
     "iso": "EST",
     "score": 54,
     "rank": 1
    },
    {
     "iso": "ETH",
     "score": 11,
     "rank": 10
    },
    {
     "iso": "FIN",
     "score": 67,
     "rank": 1
    },
    {
     "iso": "FJI",
     "score": 52,
     "rank": 3
    },
    {
     "iso": "FRA",
     "score": 72,
     "rank": 1
    },
    {
     "iso": "GAB",
     "score": 7,
     "rank": 11
    },
    {
     "iso": "GBR",
     "score": 72,
     "rank": 2
    },
    {
     "iso": "GEO",
     "score": 20,
     "rank": 10
    },
    {
     "iso": "GHA",
     "score": 10,
     "rank": 8
    },
    {
     "iso": "GIN",
     "score": 15,
     "rank": 13
    },
    {
     "iso": "GMB",
     "score": 16,
     "rank": 6
    },
    {
     "iso": "GRC",
     "score": 59,
     "rank": 1
    },
    {
     "iso": "GTM",
     "score": 20,
     "rank": 10
    },
    {
     "iso": "GUY",
     "score": 37,
     "rank": 3
    },
    {
     "iso": "HKG",
     "score": 62,
     "rank": 4
    },
    {
     "iso": "HND",
     "score": 24,
     "rank": 9
    },
    {
     "iso": "HRV",
     "score": 45,
     "rank": 3
    },
    {
     "iso": "HTI",
     "score": 0,
     "rank": 15
    },
    {
     "iso": "HUN",
     "score": 55,
     "rank": 1
    },
    {
     "iso": "IDN",
     "score": 23,
     "rank": 13
    },
    {
     "iso": "IND",
     "score": 33,
     "rank": 7
    },
    {
     "iso": "IRL",
     "score": 71,
     "rank": 1
    },
    {
     "iso": "IRN",
     "score": 25,
     "rank": 7
    },
    {
     "iso": "IRQ",
     "score": 20,
     "rank": 7
    },
    {
     "iso": "ISL",
     "score": 80,
     "rank": 2
    },
    {
     "iso": "ISR",
     "score": 87,
     "rank": 1
    },
    {
     "iso": "ITA",
     "score": 68,
     "rank": 1
    },
    {
     "iso": "JAM",
     "score": 19,
     "rank": 7
    },
    {
     "iso": "JOR",
     "score": 40,
     "rank": 3
    },
    {
     "iso": "JPN",
     "score": 56,
     "rank": 3
    },
    {
     "iso": "KAZ",
     "score": 41,
     "rank": 3
    },
    {
     "iso": "KEN",
     "score": 7,
     "rank": 13
    },
    {
     "iso": "KGZ",
     "score": 23,
     "rank": 12
    },
    {
     "iso": "KHM",
     "score": 63,
     "rank": 1
    },
    {
     "iso": "KIR",
     "score": 0,
     "rank": 4
    },
    {
     "iso": "KOR",
     "score": 52,
     "rank": 2
    },
    {
     "iso": "KWT",
     "score": 35,
     "rank": 4
    },
    {
     "iso": "LAO",
     "score": 36,
     "rank": 4
    },
    {
     "iso": "LBN",
     "score": 25,
     "rank": 7
    },
    {
     "iso": "LBR",
     "score": 11,
     "rank": 11
    },
    {
     "iso": "LBY",
     "score": 16,
     "rank": 8
    },
    {
     "iso": "LKA",
     "score": 57,
     "rank": 3
    },
    {
     "iso": "LSO",
     "score": 8,
     "rank": 9
    },
    {
     "iso": "LTU",
     "score": 62,
     "rank": 2
    },
    {
     "iso": "LUX",
     "score": 66,
     "rank": 1
    },
    {
     "iso": "LVA",
     "score": 45,
     "rank": 3
    },
    {
     "iso": "MAR",
     "score": 49,
     "rank": 2
    },
    {
     "iso": "MCO",
     "score": 66,
     "rank": 4
    },
    {
     "iso": "MDA",
     "score": 21,
     "rank": 15
    },
    {
     "iso": "MDG",
     "score": 11,
     "rank": 15
    },
    {
     "iso": "MEX",
     "score": 38,
     "rank": 4
    },
    {
     "iso": "MLI",
     "score": 10,
     "rank": 8
    },
    {
     "iso": "MLT",
     "score": 88,
     "rank": 1
    },
    {
     "iso": "MMR",
     "score": 12,
     "rank": 13
    },
    {
     "iso": "MNG",
     "score": 67,
     "rank": 1
    },
    {
     "iso": "MOZ",
     "score": 13,
     "rank": 11
    },
    {
     "iso": "MRT",
     "score": 10,
     "rank": 13
    },
    {
     "iso": "MUS",
     "score": 63,
     "rank": 4
    },
    {
     "iso": "MWI",
     "score": 16,
     "rank": 7
    },
    {
     "iso": "MYS",
     "score": 60,
     "rank": 2
    },
    {
     "iso": "NAM",
     "score": 16,
     "rank": 8
    },
    {
     "iso": "NER",
     "score": 6,
     "rank": 1
    },
    {
     "iso": "NGA",
     "score": 9,
     "rank": 7
    },
    {
     "iso": "NIC",
     "score": 8,
     "rank": 5
    },
    {
     "iso": "NLD",
     "score": 67,
     "rank": 1
    },
    {
     "iso": "NOR",
     "score": 68,
     "rank": 1
    },
    {
     "iso": "NPL",
     "score": 21,
     "rank": 11
    },
    {
     "iso": "NZL",
     "score": 45,
     "rank": 5
    },
    {
     "iso": "OMN",
     "score": 46,
     "rank": 7
    },
    {
     "iso": "PAK",
     "score": 22,
     "rank": 9
    },
    {
     "iso": "PAN",
     "score": 55,
     "rank": 4
    },
    {
     "iso": "PER",
     "score": 36,
     "rank": 8
    },
    {
     "iso": "PHL",
     "score": 22,
     "rank": 8
    },
    {
     "iso": "PNG",
     "score": 7,
     "rank": 8
    },
    {
     "iso": "POL",
     "score": 54,
     "rank": 2
    },
    {
     "iso": "PRT",
     "score": 76,
     "rank": 1
    },
    {
     "iso": "PRY",
     "score": 31,
     "rank": 4
    },
    {
     "iso": "QAT",
     "score": 80,
     "rank": 1
    },
    {
     "iso": "ROU",
     "score": 36,
     "rank": 3
    },
    {
     "iso": "RUS",
     "score": 37,
     "rank": 6
    },
    {
     "iso": "RWA",
     "score": 14,
     "rank": 11
    },
    {
     "iso": "SAU",
     "score": 64,
     "rank": 3
    },
    {
     "iso": "SDN",
     "score": 11,
     "rank": 7
    },
    {
     "iso": "SEN",
     "score": 15,
     "rank": 5
    },
    {
     "iso": "SGP",
     "score": 79,
     "rank": 4
    },
    {
     "iso": "SLE",
     "score": 12,
     "rank": 14
    },
    {
     "iso": "SLV",
     "score": 56,
     "rank": 12
    },
    {
     "iso": "SMR",
     "score": 74,
     "rank": 1
    },
    {
     "iso": "SOM",
     "score": 8,
     "rank": 8
    },
    {
     "iso": "SRB",
     "score": 49,
     "rank": 2
    },
    {
     "iso": "SSD",
     "score": 10,
     "rank": 8
    },
    {
     "iso": "SUR",
     "score": 37,
     "rank": 8
    },
    {
     "iso": "SVK",
     "score": 50,
     "rank": 3
    },
    {
     "iso": "SVN",
     "score": 51,
     "rank": 2
    },
    {
     "iso": "SWE",
     "score": 65,
     "rank": 1
    },
    {
     "iso": "SWZ",
     "score": 20,
     "rank": 14
    },
    {
     "iso": "SYC",
     "score": 79,
     "rank": 1
    },
    {
     "iso": "SYR",
     "score": 4,
     "rank": 10
    },
    {
     "iso": "TCD",
     "score": 8,
     "rank": 15
    },
    {
     "iso": "TGO",
     "score": 11,
     "rank": 6
    },
    {
     "iso": "THA",
     "score": 28,
     "rank": 5
    },
    {
     "iso": "TJK",
     "score": 29,
     "rank": 9
    },
    {
     "iso": "TLS",
     "score": 0,
     "rank": 7
    },
    {
     "iso": "TTO",
     "score": 35,
     "rank": 4
    },
    {
     "iso": "TUN",
     "score": 33,
     "rank": 4
    },
    {
     "iso": "TUR",
     "score": 60,
     "rank": 1
    },
    {
     "iso": "TWN",
     "score": 29,
     "rank": 12
    },
    {
     "iso": "TZA",
     "score": 0,
     "rank": 7
    },
    {
     "iso": "UGA",
     "score": 6,
     "rank": 8
    },
    {
     "iso": "UKR",
     "score": 18,
     "rank": 8
    },
    {
     "iso": "URY",
     "score": 86,
     "rank": 1
    },
    {
     "iso": "USA",
     "score": 60,
     "rank": 1
    },
    {
     "iso": "UZB",
     "score": 33,
     "rank": 14
    },
    {
     "iso": "VEN",
     "score": 16,
     "rank": 11
    },
    {
     "iso": "VNM",
     "score": 20,
     "rank": 9
    },
    {
     "iso": "VUT",
     "score": 17,
     "rank": 5
    },
    {
     "iso": "YEM",
     "score": 10,
     "rank": 5
    },
    {
     "iso": "ZAF",
     "score": 16,
     "rank": 6
    },
    {
     "iso": "ZMB",
     "score": 7,
     "rank": 9
    },
    {
     "iso": "ZWE",
     "score": 26,
     "rank": 10
    }
   ]
  },
  {
   "label": "Month 1",
   "data": [
    {
     "iso": "AFG",
     "score": 6,
     "rank": 6
    },
    {
     "iso": "AGO",
     "score": 10,
     "rank": 9
    },
    {
     "iso": "ALB",
     "score": 3,
     "rank": 4
    },
    {
     "iso": "AND",
     "score": 6,
     "rank": 2
    },
    {
     "iso": "ARE",
     "score": 27,
     "rank": 1
    },
    {
     "iso": "ARG",
     "score": 3,
     "rank": 4
    },
    {
     "iso": "AUS",
     "score": 7,
     "rank": 14
    },
    {
     "iso": "AUT",
     "score": 7,
     "rank": 2
    },
    {
     "iso": "AZE",
     "score": 4,
     "rank": 3
    },
    {
     "iso": "BEL",
     "score": 5,
     "rank": 1
    },
    {
     "iso": "BEN",
     "score": 10,
     "rank": 7
    },
    {
     "iso": "BFA",
     "score": 0,
     "rank": 15
    },
    {
     "iso": "BGD",
     "score": 4,
     "rank": 10
    },
    {
     "iso": "BGR",
     "score": 5,
     "rank": 8
    },
    {
     "iso": "BHR",
     "score": 17,
     "rank": 11
    },
    {
     "iso": "BHS",
     "score": 8,
     "rank": 5
    },
    {
     "iso": "BIH",
     "score": 0,
     "rank": 5
    },
    {
     "iso": "BLR",
     "score": 0,
     "rank": 7
    },
    {
     "iso": "BLZ",
     "score": 2,
     "rank": 11
    },
    {
     "iso": "BOL",
     "score": 6,
     "rank": 4
    },
    {
     "iso": "BRA",
     "score": 10,
     "rank": 2
    },
    {
     "iso": "BRB",
     "score": 18,
     "rank": 3
    },
    {
     "iso": "BRN",
     "score": 5,
     "rank": 3
    },
    {
     "iso": "BTN",
     "score": 42,
     "rank": 1
    },
    {
     "iso": "BWA",
     "score": 5,
     "rank": 8
    },
    {
     "iso": "CAF",
     "score": 6,
     "rank": 15
    },
    {
     "iso": "CAN",
     "score": 6,
     "rank": 1
    },
    {
     "iso": "CHE",
     "score": 10,
     "rank": 1
    },
    {
     "iso": "CHL",
     "score": 3,
     "rank": 1
    },
    {
     "iso": "CHN",
     "score": 3,
     "rank": 3
    },
    {
     "iso": "CIV",
     "score": 5,
     "rank": 6
    },
    {
     "iso": "CMR",
     "score": 0,
     "rank": 15
    },
    {
     "iso": "COD",
     "score": 0,
     "rank": 8
    },
    {
     "iso": "COL",
     "score": 7,
     "rank": 14
    },
    {
     "iso": "CPV",
     "score": 7,
     "rank": 8
    },
    {
     "iso": "CRI",
     "score": 8,
     "rank": 2
    },
    {
     "iso": "CUB",
     "score": 32,
     "rank": 1
    },
    {
     "iso": "CYP",
     "score": 8,
     "rank": 1
    },
    {
     "iso": "CZE",
     "score": 7,
     "rank": 2
    },
    {
     "iso": "DEU",
     "score": 7,
     "rank": 2
    },
    {
     "iso": "DJI",
     "score": 10,
     "rank": 10
    },
    {
     "iso": "DMA",
     "score": 20,
     "rank": 2
    },
    {
     "iso": "DNK",
     "score": 7,
     "rank": 1
    },
    {
     "iso": "DOM",
     "score": 9,
     "rank": 1
    },
    {
     "iso": "DZA",
     "score": 1,
     "rank": 9
    },
    {
     "iso": "ECU",
     "score": 6,
     "rank": 1
    },
    {
     "iso": "EGY",
     "score": 3,
     "rank": 15
    },
    {
     "iso": "ESP",
     "score": 8,
     "rank": 1
    },
    {
     "iso": "EST",
     "score": 5,
     "rank": 1
    },
    {
     "iso": "ETH",
     "score": 10,
     "rank": 10
    },
    {
     "iso": "FIN",
     "score": 7,
     "rank": 1
    },
    {
     "iso": "FJI",
     "score": 8,
     "rank": 3
    },
    {
     "iso": "FRA",
     "score": 5,
     "rank": 1
    },
    {
     "iso": "GAB",
     "score": 6,
     "rank": 11
    },
    {
     "iso": "GBR",
     "score": 11,
     "rank": 2
    },
    {
     "iso": "GEO",
     "score": 5,
     "rank": 10
    },
    {
     "iso": "GHA",
     "score": 7,
     "rank": 8
    },
    {
     "iso": "GIN",
     "score": 8,
     "rank": 13
    },
    {
     "iso": "GMB",
     "score": 8,
     "rank": 6
    },
    {
     "iso": "GRC",
     "score": 8,
     "rank": 1
    },
    {
     "iso": "GTM",
     "score": 8,
     "rank": 10
    },
    {
     "iso": "GUY",
     "score": 3,
     "rank": 3
    },
    {
     "iso": "HKG",
     "score": 12,
     "rank": 4
    },
    {
     "iso": "HND",
     "score": 0,
     "rank": 9
    },
    {
     "iso": "HRV",
     "score": 7,
     "rank": 3
    },
    {
     "iso": "HUN",
     "score": 6,
     "rank": 1
    },
    {
     "iso": "IDN",
     "score": 6,
     "rank": 13
    },
    {
     "iso": "IND",
     "score": 6,
     "rank": 7
    },
    {
     "iso": "IRL",
     "score": 6,
     "rank": 1
    },
    {
     "iso": "IRN",
     "score": 3,
     "rank": 7
    },
    {
     "iso": "IRQ",
     "score": 9,
     "rank": 7
    },
    {
     "iso": "ISL",
     "score": 8,
     "rank": 2
    },
    {
     "iso": "ISR",
     "score": 23,
     "rank": 1
    },
    {
     "iso": "ITA",
     "score": 7,
     "rank": 1
    },
    {
     "iso": "JAM",
     "score": 6,
     "rank": 7
    },
    {
     "iso": "JOR",
     "score": 9,
     "rank": 3
    },
    {
     "iso": "JPN",
     "score": 3,
     "rank": 3
    },
    {
     "iso": "KAZ",
     "score": 3,
     "rank": 3
    },
    {
     "iso": "KEN",
     "score": 3,
     "rank": 13
    },
    {
     "iso": "KGZ",
     "score": 15,
     "rank": 12
    },
    {
     "iso": "KHM",
     "score": 4,
     "rank": 1
    },
    {
     "iso": "KOR",
     "score": 7,
     "rank": 2
    },
    {
     "iso": "KWT",
     "score": 10,
     "rank": 4
    },
    {
     "iso": "LAO",
     "score": 5,
     "rank": 4
    },
    {
     "iso": "LBN",
     "score": 3,
     "rank": 7
    },
    {
     "iso": "LBR",
     "score": 10,
     "rank": 11
    },
    {
     "iso": "LBY",
     "score": 10,
     "rank": 8
    },
    {
     "iso": "LKA",
     "score": 4,
     "rank": 3
    },
    {
     "iso": "LSO",
     "score": 0,
     "rank": 9
    },
    {
     "iso": "LTU",
     "score": 7,
     "rank": 2
    },
    {
     "iso": "LUX",
     "score": 7,
     "rank": 1
    },
    {
     "iso": "LVA",
     "score": 0,
     "rank": 3
    },
    {
     "iso": "MAR",
     "score": 9,
     "rank": 2
    },
    {
     "iso": "MCO",
     "score": 7,
     "rank": 4
    },
    {
     "iso": "MDA",
     "score": 3,
     "rank": 15
    },
    {
     "iso": "MDG",
     "score": 10,
     "rank": 15
    },
    {
     "iso": "MEX",
     "score": 3,
     "rank": 4
    },
    {
     "iso": "MLI",
     "score": 9,
     "rank": 8
    },
    {
     "iso": "MLT",
     "score": 14,
     "rank": 1
    },
    {
     "iso": "MMR",
     "score": 6,
     "rank": 13
    },
    {
     "iso": "MNG",
     "score": 6,
     "rank": 1
    },
    {
     "iso": "MOZ",
     "score": 9,
     "rank": 11
    },
    {
     "iso": "MRT",
     "score": 9,
     "rank": 13
    },
    {
     "iso": "MUS",
     "score": 5,
     "rank": 4
    },
    {
     "iso": "MWI",
     "score": 11,
     "rank": 7
    },
    {
     "iso": "MYS",
     "score": 6,
     "rank": 2
    },
    {
     "iso": "NAM",
     "score": 12,
     "rank": 8
    },
    {
     "iso": "NER",
     "score": 3,
     "rank": 1
    },
    {
     "iso": "NGA",
     "score": 0,
     "rank": 7
    },
    {
     "iso": "NIC",
     "score": 0,
     "rank": 5
    },
    {
     "iso": "NLD",
     "score": 5,
     "rank": 1
    },
    {
     "iso": "NOR",
     "score": 4,
     "rank": 1
    },
    {
     "iso": "NPL",
     "score": 3,
     "rank": 11
    },
    {
     "iso": "NZL",
     "score": 3,
     "rank": 5
    },
    {
     "iso": "OMN",
     "score": 9,
     "rank": 7
    },
    {
     "iso": "PAK",
     "score": 3,
     "rank": 9
    },
    {
     "iso": "PAN",
     "score": 1,
     "rank": 4
    },
    {
     "iso": "PER",
     "score": 4,
     "rank": 8
    },
    {
     "iso": "PHL",
     "score": 3,
     "rank": 8
    },
    {
     "iso": "PNG",
     "score": 3,
     "rank": 8
    },
    {
     "iso": "POL",
     "score": 7,
     "rank": 2
    },
    {
     "iso": "PRT",
     "score": 7,
     "rank": 1
    },
    {
     "iso": "PRY",
     "score": 3,
     "rank": 4
    },
    {
     "iso": "QAT",
     "score": 0,
     "rank": 1
    },
    {
     "iso": "ROU",
     "score": 6,
     "rank": 3
    },
    {
     "iso": "RUS",
     "score": 1,
     "rank": 6
    },
    {
     "iso": "RWA",
     "score": 7,
     "rank": 11
    },
    {
     "iso": "SAU",
     "score": 12,
     "rank": 3
    },
    {
     "iso": "SDN",
     "score": 7,
     "rank": 7
    },
    {
     "iso": "SEN",
     "score": 9,
     "rank": 5
    },
    {
     "iso": "SGP",
     "score": 6,
     "rank": 4
    },
    {
     "iso": "SLE",
     "score": 8,
     "rank": 14
    },
    {
     "iso": "SLV",
     "score": 2,
     "rank": 12
    },
    {
     "iso": "SMR",
     "score": 24,
     "rank": 1
    },
    {
     "iso": "SOM",
     "score": 6,
     "rank": 8
    },
    {
     "iso": "SRB",
     "score": 11,
     "rank": 2
    },
    {
     "iso": "SSD",
     "score": 6,
     "rank": 8
    },
    {
     "iso": "SUR",
     "score": 6,
     "rank": 8
    },
    {
     "iso": "SVK",
     "score": 6,
     "rank": 3
    },
    {
     "iso": "SVN",
     "score": 7,
     "rank": 2
    },
    {
     "iso": "SWE",
     "score": 7,
     "rank": 1
    },
    {
     "iso": "SWZ",
     "score": 9,
     "rank": 14
    },
    {
     "iso": "SYC",
     "score": 25,
     "rank": 1
    },
    {
     "iso": "SYR",
     "score": 0,
     "rank": 10
    },
    {
     "iso": "TCD",
     "score": 8,
     "rank": 15
    },
    {
     "iso": "TGO",
     "score": 6,
     "rank": 6
    },
    {
     "iso": "THA",
     "score": 0,
     "rank": 5
    },
    {
     "iso": "TLS",
     "score": 10,
     "rank": 7
    },
    {
     "iso": "TTO",
     "score": 3,
     "rank": 4
    },
    {
     "iso": "TUN",
     "score": 10,
     "rank": 4
    },
    {
     "iso": "TUR",
     "score": 6,
     "rank": 1
    },
    {
     "iso": "TWN",
     "score": 4,
     "rank": 12
    },
    {
     "iso": "UGA",
     "score": 3,
     "rank": 8
    },
    {
     "iso": "UKR",
     "score": 3,
     "rank": 8
    },
    {
     "iso": "URY",
     "score": 13,
     "rank": 1
    },
    {
     "iso": "USA",
     "score": 5,
     "rank": 1
    },
    {
     "iso": "UZB",
     "score": 13,
     "rank": 14
    },
    {
     "iso": "VEN",
     "score": 3,
     "rank": 11
    },
    {
     "iso": "VNM",
     "score": 3,
     "rank": 9
    },
    {
     "iso": "VUT",
     "score": 10,
     "rank": 5
    },
    {
     "iso": "YEM",
     "score": 11,
     "rank": 5
    },
    {
     "iso": "ZAF",
     "score": 3,
     "rank": 6
    },
    {
     "iso": "ZMB",
     "score": 3,
     "rank": 9
    },
    {
     "iso": "ZWE",
     "score": 7,
     "rank": 10
    }
   ]
  },
  {
   "label": "Month 2",
   "data": [
    {
     "iso": "AFG",
     "score": 6,
     "rank": 6
    },
    {
     "iso": "AGO",
     "score": 10,
     "rank": 9
    },
    {
     "iso": "ALB",
     "score": 4,
     "rank": 4
    },
    {
     "iso": "AND",
     "score": 13,
     "rank": 2
    },
    {
     "iso": "ARE",
     "score": 40,
     "rank": 1
    },
    {
     "iso": "ARG",
     "score": 4,
     "rank": 4
    },
    {
     "iso": "AUS",
     "score": 16,
     "rank": 14
    },
    {
     "iso": "AUT",
     "score": 11,
     "rank": 2
    },
    {
     "iso": "AZE",
     "score": 8,
     "rank": 3
    },
    {
     "iso": "BEL",
     "score": 9,
     "rank": 1
    },
    {
     "iso": "BEN",
     "score": 13,
     "rank": 7
    },
    {
     "iso": "BFA",
     "score": 0,
     "rank": 15
    },
    {
     "iso": "BGD",
     "score": 7,
     "rank": 10
    },
    {
     "iso": "BGR",
     "score": 10,
     "rank": 8
    },
    {
     "iso": "BHR",
     "score": 25,
     "rank": 11
    },
    {
     "iso": "BHS",
     "score": 17,
     "rank": 5
    },
    {
     "iso": "BLR",
     "score": 3,
     "rank": 7
    },
    {
     "iso": "BLZ",
     "score": 14,
     "rank": 11
    },
    {
     "iso": "BOL",
     "score": 7,
     "rank": 4
    },
    {
     "iso": "BRA",
     "score": 12,
     "rank": 2
    },
    {
     "iso": "BRB",
     "score": 20,
     "rank": 3
    },
    {
     "iso": "BRN",
     "score": 17,
     "rank": 3
    },
    {
     "iso": "BTN",
     "score": 43,
     "rank": 1
    },
    {
     "iso": "BWA",
     "score": 6,
     "rank": 8
    },
    {
     "iso": "CAF",
     "score": 7,
     "rank": 15
    },
    {
     "iso": "CAN",
     "score": 10,
     "rank": 1
    },
    {
     "iso": "CHE",
     "score": 14,
     "rank": 1
    },
    {
     "iso": "CHL",
     "score": 18,
     "rank": 1
    },
    {
     "iso": "CHN",
     "score": 4,
     "rank": 3
    },
    {
     "iso": "CIV",
     "score": 15,
     "rank": 6
    },
    {
     "iso": "CMR",
     "score": 0,
     "rank": 15
    },
    {
     "iso": "COD",
     "score": 0,
     "rank": 8
    },
    {
     "iso": "COL",
     "score": 9,
     "rank": 14
    },
    {
     "iso": "CPV",
     "score": 11,
     "rank": 8
    },
    {
     "iso": "CRI",
     "score": 10,
     "rank": 2
    },
    {
     "iso": "CUB",
     "score": 51,
     "rank": 1
    },
    {
     "iso": "CYP",
     "score": 13,
     "rank": 1
    },
    {
     "iso": "CZE",
     "score": 9,
     "rank": 2
    },
    {
     "iso": "DEU",
     "score": 9,
     "rank": 2
    },
    {
     "iso": "DJI",
     "score": 10,
     "rank": 10
    },
    {
     "iso": "DMA",
     "score": 28,
     "rank": 2
    },
    {
     "iso": "DNK",
     "score": 12,
     "rank": 1
    },
    {
     "iso": "DOM",
     "score": 13,
     "rank": 1
    },
    {
     "iso": "ECU",
     "score": 7,
     "rank": 1
    },
    {
     "iso": "EGY",
     "score": 6,
     "rank": 15
    },
    {
     "iso": "ESP",
     "score": 11,
     "rank": 1
    },
    {
     "iso": "EST",
     "score": 9,
     "rank": 1
    },
    {
     "iso": "ETH",
     "score": 10,
     "rank": 10
    },
    {
     "iso": "FIN",
     "score": 10,
     "rank": 1
    },
    {
     "iso": "FJI",
     "score": 14,
     "rank": 3
    },
    {
     "iso": "FRA",
     "score": 11,
     "rank": 1
    },
    {
     "iso": "GAB",
     "score": 6,
     "rank": 11
    },
    {
     "iso": "GBR",
     "score": 19,
     "rank": 2
    },
    {
     "iso": "GEO",
     "score": 7,
     "rank": 10
    },
    {
     "iso": "GHA",
     "score": 10,
     "rank": 8
    },
    {
     "iso": "GIN",
     "score": 12,
     "rank": 13
    },
    {
     "iso": "GMB",
     "score": 13,
     "rank": 6
    },
    {
     "iso": "GRC",
     "score": 13,
     "rank": 1
    },
    {
     "iso": "GTM",
     "score": 6,
     "rank": 10
    },
    {
     "iso": "GUY",
     "score": 11,
     "rank": 3
    },
    {
     "iso": "HKG",
     "score": 20,
     "rank": 4
    },
    {
     "iso": "HND",
     "score": 2,
     "rank": 9
    },
    {
     "iso": "HRV",
     "score": 8,
     "rank": 3
    },
    {
     "iso": "HUN",
     "score": 11,
     "rank": 1
    },
    {
     "iso": "IDN",
     "score": 7,
     "rank": 13
    },
    {
     "iso": "IND",
     "score": 9,
     "rank": 7
    },
    {
     "iso": "IRL",
     "score": 10,
     "rank": 1
    },
    {
     "iso": "IRN",
     "score": 7,
     "rank": 7
    },
    {
     "iso": "IRQ",
     "score": 12,
     "rank": 7
    },
    {
     "iso": "ISL",
     "score": 10,
     "rank": 2
    },
    {
     "iso": "ISR",
     "score": 50,
     "rank": 1
    },
    {
     "iso": "ITA",
     "score": 9,
     "rank": 1
    },
    {
     "iso": "JAM",
     "score": 8,
     "rank": 7
    },
    {
     "iso": "JOR",
     "score": 10,
     "rank": 3
    },
    {
     "iso": "JPN",
     "score": 4,
     "rank": 3
    },
    {
     "iso": "KAZ",
     "score": 3,
     "rank": 3
    },
    {
     "iso": "KEN",
     "score": 7,
     "rank": 13
    },
    {
     "iso": "KGZ",
     "score": 21,
     "rank": 12
    },
    {
     "iso": "KHM",
     "score": 9,
     "rank": 1
    },
    {
     "iso": "KOR",
     "score": 12,
     "rank": 2
    },
    {
     "iso": "KWT",
     "score": 11,
     "rank": 4
    },
    {
     "iso": "LAO",
     "score": 15,
     "rank": 4
    },
    {
     "iso": "LBN",
     "score": 11,
     "rank": 7
    },
    {
     "iso": "LBR",
     "score": 10,
     "rank": 11
    },
    {
     "iso": "LBY",
     "score": 11,
     "rank": 8
    },
    {
     "iso": "LKA",
     "score": 8,
     "rank": 3
    },
    {
     "iso": "LSO",
     "score": 3,
     "rank": 9
    },
    {
     "iso": "LTU",
     "score": 10,
     "rank": 2
    },
    {
     "iso": "LUX",
     "score": 9,
     "rank": 1
    },
    {
     "iso": "LVA",
     "score": 3,
     "rank": 3
    },
    {
     "iso": "MAR",
     "score": 16,
     "rank": 2
    },
    {
     "iso": "MCO",
     "score": 20,
     "rank": 4
    },
    {
     "iso": "MDA",
     "score": 7,
     "rank": 15
    },
    {
     "iso": "MDG",
     "score": 16,
     "rank": 15
    },
    {
     "iso": "MEX",
     "score": 4,
     "rank": 4
    },
    {
     "iso": "MLI",
     "score": 9,
     "rank": 8
    },
    {
     "iso": "MLT",
     "score": 23,
     "rank": 1
    },
    {
     "iso": "MMR",
     "score": 7,
     "rank": 13
    },
    {
     "iso": "MNG",
     "score": 11,
     "rank": 1
    },
    {
     "iso": "MOZ",
     "score": 10,
     "rank": 11
    },
    {
     "iso": "MRT",
     "score": 7,
     "rank": 13
    },
    {
     "iso": "MUS",
     "score": 15,
     "rank": 4
    },
    {
     "iso": "MWI",
     "score": 15,
     "rank": 7
    },
    {
     "iso": "MYS",
     "score": 9,
     "rank": 2
    },
    {
     "iso": "NAM",
     "score": 13,
     "rank": 8
    },
    {
     "iso": "NER",
     "score": 13,
     "rank": 1
    },
    {
     "iso": "NGA",
     "score": 9,
     "rank": 7
    },
    {
     "iso": "NIC",
     "score": 4,
     "rank": 5
    },
    {
     "iso": "NLD",
     "score": 13,
     "rank": 1
    },
    {
     "iso": "NOR",
     "score": 9,
     "rank": 1
    },
    {
     "iso": "NPL",
     "score": 5,
     "rank": 11
    },
    {
     "iso": "NZL",
     "score": 8,
     "rank": 5
    },
    {
     "iso": "OMN",
     "score": 10,
     "rank": 7
    },
    {
     "iso": "PAK",
     "score": 6,
     "rank": 9
    },
    {
     "iso": "PAN",
     "score": 9,
     "rank": 4
    },
    {
     "iso": "PER",
     "score": 9,
     "rank": 8
    },
    {
     "iso": "PHL",
     "score": 10,
     "rank": 8
    },
    {
     "iso": "PNG",
     "score": 3,
     "rank": 8
    },
    {
     "iso": "POL",
     "score": 10,
     "rank": 2
    },
    {
     "iso": "PRT",
     "score": 12,
     "rank": 1
    },
    {
     "iso": "PRY",
     "score": 4,
     "rank": 4
    },
    {
     "iso": "QAT",
     "score": 11,
     "rank": 1
    },
    {
     "iso": "ROU",
     "score": 13,
     "rank": 3
    },
    {
     "iso": "RUS",
     "score": 6,
     "rank": 6
    },
    {
     "iso": "RWA",
     "score": 7,
     "rank": 11
    },
    {
     "iso": "SAU",
     "score": 14,
     "rank": 3
    },
    {
     "iso": "SDN",
     "score": 9,
     "rank": 7
    },
    {
     "iso": "SEN",
     "score": 10,
     "rank": 5
    },
    {
     "iso": "SGP",
     "score": 11,
     "rank": 4
    },
    {
     "iso": "SLE",
     "score": 13,
     "rank": 14
    },
    {
     "iso": "SLV",
     "score": 16,
     "rank": 12
    },
    {
     "iso": "SMR",
     "score": 51,
     "rank": 1
    },
    {
     "iso": "SOM",
     "score": 9,
     "rank": 8
    },
    {
     "iso": "SRB",
     "score": 23,
     "rank": 2
    },
    {
     "iso": "SSD",
     "score": 7,
     "rank": 8
    },
    {
     "iso": "SUR",
     "score": 14,
     "rank": 8
    },
    {
     "iso": "SVK",
     "score": 13,
     "rank": 3
    },
    {
     "iso": "SVN",
     "score": 12,
     "rank": 2
    },
    {
     "iso": "SWE",
     "score": 9,
     "rank": 1
    },
    {
     "iso": "SWZ",
     "score": 11,
     "rank": 14
    },
    {
     "iso": "SYC",
     "score": 52,
     "rank": 1
    },
    {
     "iso": "SYR",
     "score": 3,
     "rank": 10
    },
    {
     "iso": "TCD",
     "score": 8,
     "rank": 15
    },
    {
     "iso": "TGO",
     "score": 9,
     "rank": 6
    },
    {
     "iso": "THA",
     "score": 0,
     "rank": 5
    },
    {
     "iso": "TJK",
     "score": 13,
     "rank": 9
    },
    {
     "iso": "TLS",
     "score": 11,
     "rank": 7
    },
    {
     "iso": "TTO",
     "score": 3,
     "rank": 4
    },
    {
     "iso": "TUN",
     "score": 11,
     "rank": 4
    },
    {
     "iso": "TUR",
     "score": 12,
     "rank": 1
    },
    {
     "iso": "TWN",
     "score": 10,
     "rank": 12
    },
    {
     "iso": "UGA",
     "score": 3,
     "rank": 8
    },
    {
     "iso": "UKR",
     "score": 6,
     "rank": 8
    },
    {
     "iso": "URY",
     "score": 35,
     "rank": 1
    },
    {
     "iso": "USA",
     "score": 11,
     "rank": 1
    },
    {
     "iso": "UZB",
     "score": 15,
     "rank": 14
    },
    {
     "iso": "VEN",
     "score": 3,
     "rank": 11
    },
    {
     "iso": "VNM",
     "score": 8,
     "rank": 9
    },
    {
     "iso": "VUT",
     "score": 16,
     "rank": 5
    },
    {
     "iso": "YEM",
     "score": 12,
     "rank": 5
    },
    {
     "iso": "ZAF",
     "score": 4,
     "rank": 6
    },
    {
     "iso": "ZMB",
     "score": 9,
     "rank": 9
    },
    {
     "iso": "ZWE",
     "score": 13,
     "rank": 10
    }
   ]
  },
  {
   "label": "Month 3",
   "data": [
    {
     "iso": "AFG",
     "score": 7,
     "rank": 6
    },
    {
     "iso": "AGO",
     "score": 8,
     "rank": 9
    },
    {
     "iso": "ALB",
     "score": 10,
     "rank": 4
    },
    {
     "iso": "AND",
     "score": 27,
     "rank": 2
    },
    {
     "iso": "ARE",
     "score": 54,
     "rank": 1
    },
    {
     "iso": "ARG",
     "score": 10,
     "rank": 4
    },
    {
     "iso": "AUS",
     "score": 19,
     "rank": 14
    },
    {
     "iso": "AUT",
     "score": 18,
     "rank": 2
    },
    {
     "iso": "AZE",
     "score": 17,
     "rank": 3
    },
    {
     "iso": "BEL",
     "score": 14,
     "rank": 1
    },
    {
     "iso": "BEN",
     "score": 13,
     "rank": 7
    },
    {
     "iso": "BFA",
     "score": 7,
     "rank": 15
    },
    {
     "iso": "BGD",
     "score": 14,
     "rank": 10
    },
    {
     "iso": "BGR",
     "score": 19,
     "rank": 8
    },
    {
     "iso": "BHR",
     "score": 33,
     "rank": 11
    },
    {
     "iso": "BHS",
     "score": 23,
     "rank": 5
    },
    {
     "iso": "BIH",
     "score": 9,
     "rank": 5
    },
    {
     "iso": "BLR",
     "score": 3,
     "rank": 7
    },
    {
     "iso": "BLZ",
     "score": 18,
     "rank": 11
    },
    {
     "iso": "BOL",
     "score": 9,
     "rank": 4
    },
    {
     "iso": "BRA",
     "score": 16,
     "rank": 2
    },
    {
     "iso": "BRB",
     "score": 31,
     "rank": 3
    },
    {
     "iso": "BRN",
     "score": 20,
     "rank": 3
    },
    {
     "iso": "BTN",
     "score": 43,
     "rank": 1
    },
    {
     "iso": "BWA",
     "score": 12,
     "rank": 8
    },
    {
     "iso": "CAF",
     "score": 7,
     "rank": 15
    },
    {
     "iso": "CAN",
     "score": 13,
     "rank": 1
    },
    {
     "iso": "CHE",
     "score": 21,
     "rank": 1
    },
    {
     "iso": "CHL",
     "score": 31,
     "rank": 1
    },
    {
     "iso": "CHN",
     "score": 6,
     "rank": 3
    },
    {
     "iso": "CIV",
     "score": 17,
     "rank": 6
    },
    {
     "iso": "CMR",
     "score": 0,
     "rank": 15
    },
    {
     "iso": "COD",
     "score": 3,
     "rank": 8
    },
    {
     "iso": "COL",
     "score": 15,
     "rank": 14
    },
    {
     "iso": "CPV",
     "score": 13,
     "rank": 8
    },
    {
     "iso": "CRI",
     "score": 12,
     "rank": 2
    },
    {
     "iso": "CUB",
     "score": 68,
     "rank": 1
    },
    {
     "iso": "CYP",
     "score": 17,
     "rank": 1
    },
    {
     "iso": "CZE",
     "score": 14,
     "rank": 2
    },
    {
     "iso": "DEU",
     "score": 17,
     "rank": 2
    },
    {
     "iso": "DMA",
     "score": 38,
     "rank": 2
    },
    {
     "iso": "DNK",
     "score": 16,
     "rank": 1
    },
    {
     "iso": "DOM",
     "score": 21,
     "rank": 1
    },
    {
     "iso": "ECU",
     "score": 11,
     "rank": 1
    },
    {
     "iso": "EGY",
     "score": 9,
     "rank": 15
    },
    {
     "iso": "ESP",
     "score": 15,
     "rank": 1
    },
    {
     "iso": "EST",
     "score": 17,
     "rank": 1
    },
    {
     "iso": "ETH",
     "score": 10,
     "rank": 10
    },
    {
     "iso": "FIN",
     "score": 17,
     "rank": 1
    },
    {
     "iso": "FJI",
     "score": 22,
     "rank": 3
    },
    {
     "iso": "FRA",
     "score": 17,
     "rank": 1
    },
    {
     "iso": "GAB",
     "score": 7,
     "rank": 11
    },
    {
     "iso": "GBR",
     "score": 27,
     "rank": 2
    },
    {
     "iso": "GEO",
     "score": 8,
     "rank": 10
    },
    {
     "iso": "GHA",
     "score": 10,
     "rank": 8
    },
    {
     "iso": "GIN",
     "score": 15,
     "rank": 13
    },
    {
     "iso": "GMB",
     "score": 13,
     "rank": 6
    },
    {
     "iso": "GRC",
     "score": 15,
     "rank": 1
    },
    {
     "iso": "GTM",
     "score": 6,
     "rank": 10
    },
    {
     "iso": "GUY",
     "score": 22,
     "rank": 3
    },
    {
     "iso": "HKG",
     "score": 29,
     "rank": 4
    },
    {
     "iso": "HND",
     "score": 6,
     "rank": 9
    },
    {
     "iso": "HRV",
     "score": 11,
     "rank": 3
    },
    {
     "iso": "HUN",
     "score": 22,
     "rank": 1
    },
    {
     "iso": "IDN",
     "score": 9,
     "rank": 13
    },
    {
     "iso": "IND",
     "score": 15,
     "rank": 7
    },
    {
     "iso": "IRL",
     "score": 16,
     "rank": 1
    },
    {
     "iso": "IRN",
     "score": 9,
     "rank": 7
    },
    {
     "iso": "IRQ",
     "score": 16,
     "rank": 7
    },
    {
     "iso": "ISL",
     "score": 15,
     "rank": 2
    },
    {
     "iso": "ISR",
     "score": 69,
     "rank": 1
    },
    {
     "iso": "ITA",
     "score": 13,
     "rank": 1
    },
    {
     "iso": "JAM",
     "score": 15,
     "rank": 7
    },
    {
     "iso": "JOR",
     "score": 14,
     "rank": 3
    },
    {
     "iso": "JPN",
     "score": 9,
     "rank": 3
    },
    {
     "iso": "KAZ",
     "score": 15,
     "rank": 3
    },
    {
     "iso": "KEN",
     "score": 7,
     "rank": 13
    },
    {
     "iso": "KHM",
     "score": 19,
     "rank": 1
    },
    {
     "iso": "KOR",
     "score": 15,
     "rank": 2
    },
    {
     "iso": "KWT",
     "score": 15,
     "rank": 4
    },
    {
     "iso": "LAO",
     "score": 19,
     "rank": 4
    },
    {
     "iso": "LBN",
     "score": 13,
     "rank": 7
    },
    {
     "iso": "LBR",
     "score": 12,
     "rank": 11
    },
    {
     "iso": "LKA",
     "score": 14,
     "rank": 3
    },
    {
     "iso": "LSO",
     "score": 3,
     "rank": 9
    },
    {
     "iso": "LTU",
     "score": 14,
     "rank": 2
    },
    {
     "iso": "LUX",
     "score": 16,
     "rank": 1
    },
    {
     "iso": "LVA",
     "score": 6,
     "rank": 3
    },
    {
     "iso": "MAR",
     "score": 21,
     "rank": 2
    },
    {
     "iso": "MCO",
     "score": 31,
     "rank": 4
    },
    {
     "iso": "MDA",
     "score": 14,
     "rank": 15
    },
    {
     "iso": "MEX",
     "score": 8,
     "rank": 4
    },
    {
     "iso": "MLI",
     "score": 10,
     "rank": 8
    },
    {
     "iso": "MLT",
     "score": 37,
     "rank": 1
    },
    {
     "iso": "MMR",
     "score": 8,
     "rank": 13
    },
    {
     "iso": "MNG",
     "score": 51,
     "rank": 1
    },
    {
     "iso": "MOZ",
     "score": 12,
     "rank": 11
    },
    {
     "iso": "MRT",
     "score": 11,
     "rank": 13
    },
    {
     "iso": "MUS",
     "score": 14,
     "rank": 4
    },
    {
     "iso": "MWI",
     "score": 17,
     "rank": 7
    },
    {
     "iso": "MYS",
     "score": 15,
     "rank": 2
    },
    {
     "iso": "NAM",
     "score": 14,
     "rank": 8
    },
    {
     "iso": "NER",
     "score": 5,
     "rank": 1
    },
    {
     "iso": "NGA",
     "score": 12,
     "rank": 7
    },
    {
     "iso": "NIC",
     "score": 4,
     "rank": 5
    },
    {
     "iso": "NLD",
     "score": 17,
     "rank": 1
    },
    {
     "iso": "NOR",
     "score": 13,
     "rank": 1
    },
    {
     "iso": "NPL",
     "score": 6,
     "rank": 11
    },
    {
     "iso": "NZL",
     "score": 15,
     "rank": 5
    },
    {
     "iso": "OMN",
     "score": 10,
     "rank": 7
    },
    {
     "iso": "PAK",
     "score": 9,
     "rank": 9
    },
    {
     "iso": "PAN",
     "score": 12,
     "rank": 4
    },
    {
     "iso": "PER",
     "score": 12,
     "rank": 8
    },
    {
     "iso": "PHL",
     "score": 10,
     "rank": 8
    },
    {
     "iso": "PNG",
     "score": 3,
     "rank": 8
    },
    {
     "iso": "POL",
     "score": 13,
     "rank": 2
    },
    {
     "iso": "PRT",
     "score": 17,
     "rank": 1
    },
    {
     "iso": "PRY",
     "score": 6,
     "rank": 4
    },
    {
     "iso": "QAT",
     "score": 19,
     "rank": 1
    },
    {
     "iso": "ROU",
     "score": 19,
     "rank": 3
    },
    {
     "iso": "RUS",
     "score": 12,
     "rank": 6
    },
    {
     "iso": "RWA",
     "score": 7,
     "rank": 11
    },
    {
     "iso": "SAU",
     "score": 22,
     "rank": 3
    },
    {
     "iso": "SDN",
     "score": 10,
     "rank": 7
    },
    {
     "iso": "SEN",
     "score": 11,
     "rank": 5
    },
    {
     "iso": "SGP",
     "score": 24,
     "rank": 4
    },
    {
     "iso": "SLE",
     "score": 13,
     "rank": 14
    },
    {
     "iso": "SLV",
     "score": 23,
     "rank": 12
    },
    {
     "iso": "SMR",
     "score": 73,
     "rank": 1
    },
    {
     "iso": "SOM",
     "score": 10,
     "rank": 8
    },
    {
     "iso": "SRB",
     "score": 29,
     "rank": 2
    },
    {
     "iso": "SSD",
     "score": 13,
     "rank": 8
    },
    {
     "iso": "SUR",
     "score": 18,
     "rank": 8
    },
    {
     "iso": "SVK",
     "score": 19,
     "rank": 3
    },
    {
     "iso": "SVN",
     "score": 17,
     "rank": 2
    },
    {
     "iso": "SWE",
     "score": 13,
     "rank": 1
    },
    {
     "iso": "SWZ",
     "score": 16,
     "rank": 14
    },
    {
     "iso": "SYC",
     "score": 65,
     "rank": 1
    },
    {
     "iso": "SYR",
     "score": 3,
     "rank": 10
    },
    {
     "iso": "TGO",
     "score": 9,
     "rank": 6
    },
    {
     "iso": "THA",
     "score": 8,
     "rank": 5
    },
    {
     "iso": "TJK",
     "score": 21,
     "rank": 9
    },
    {
     "iso": "TLS",
     "score": 21,
     "rank": 7
    },
    {
     "iso": "TTO",
     "score": 8,
     "rank": 4
    },
    {
     "iso": "TUN",
     "score": 14,
     "rank": 4
    },
    {
     "iso": "TUR",
     "score": 19,
     "rank": 1
    },
    {
     "iso": "TWN",
     "score": 12,
     "rank": 12
    },
    {
     "iso": "UGA",
     "score": 7,
     "rank": 8
    },
    {
     "iso": "UKR",
     "score": 7,
     "rank": 8
    },
    {
     "iso": "URY",
     "score": 49,
     "rank": 1
    },
    {
     "iso": "USA",
     "score": 22,
     "rank": 1
    },
    {
     "iso": "UZB",
     "score": 16,
     "rank": 14
    },
    {
     "iso": "VEN",
     "score": 3,
     "rank": 11
    },
    {
     "iso": "VNM",
     "score": 10,
     "rank": 9
    },
    {
     "iso": "VUT",
     "score": 17,
     "rank": 5
    },
    {
     "iso": "YEM",
     "score": 10,
     "rank": 5
    },
    {
     "iso": "ZAF",
     "score": 6,
     "rank": 6
    },
    {
     "iso": "ZMB",
     "score": 4,
     "rank": 9
    },
    {
     "iso": "ZWE",
     "score": 16,
     "rank": 10
    }
   ]
  },
  {
   "label": "Month 4",
   "data": [
    {
     "iso": "AFG",
     "score": 6,
     "rank": 6
    },
    {
     "iso": "AGO",
     "score": 11,
     "rank": 9
    },
    {
     "iso": "ALB",
     "score": 16,
     "rank": 4
    },
    {
     "iso": "AND",
     "score": 33,
     "rank": 2
    },
    {
     "iso": "ARE",
     "score": 65,
     "rank": 1
    },
    {
     "iso": "ARG",
     "score": 16,
     "rank": 4
    },
    {
     "iso": "AUS",
     "score": 24,
     "rank": 14
    },
    {
     "iso": "AUT",
     "score": 25,
     "rank": 2
    },
    {
     "iso": "AZE",
     "score": 22,
     "rank": 3
    },
    {
     "iso": "BEL",
     "score": 23,
     "rank": 1
    },
    {
     "iso": "BGD",
     "score": 6,
     "rank": 10
    },
    {
     "iso": "BGR",
     "score": 21,
     "rank": 8
    },
    {
     "iso": "BHR",
     "score": 41,
     "rank": 11
    },
    {
     "iso": "BHS",
     "score": 28,
     "rank": 5
    },
    {
     "iso": "BIH",
     "score": 14,
     "rank": 5
    },
    {
     "iso": "BLR",
     "score": 4,
     "rank": 7
    },
    {
     "iso": "BLZ",
     "score": 22,
     "rank": 11
    },
    {
     "iso": "BOL",
     "score": 13,
     "rank": 4
    },
    {
     "iso": "BRA",
     "score": 21,
     "rank": 2
    },
    {
     "iso": "BRB",
     "score": 38,
     "rank": 3
    },
    {
     "iso": "BRN",
     "score": 33,
     "rank": 3
    },
    {
     "iso": "BTN",
     "score": 68,
     "rank": 1
    },
    {
     "iso": "BWA",
     "score": 13,
     "rank": 8
    },
    {
     "iso": "CAN",
     "score": 20,
     "rank": 1
    },
    {
     "iso": "CHE",
     "score": 33,
     "rank": 1
    },
    {
     "iso": "CHL",
     "score": 48,
     "rank": 1
    },
    {
     "iso": "CHN",
     "score": 17,
     "rank": 3
    },
    {
     "iso": "CIV",
     "score": 17,
     "rank": 6
    },
    {
     "iso": "CMR",
     "score": 1,
     "rank": 15
    },
    {
     "iso": "COD",
     "score": 3,
     "rank": 8
    },
    {
     "iso": "COL",
     "score": 22,
     "rank": 14
    },
    {
     "iso": "CPV",
     "score": 20,
     "rank": 8
    },
    {
     "iso": "CRI",
     "score": 16,
     "rank": 2
    },
    {
     "iso": "CYP",
     "score": 23,
     "rank": 1
    },
    {
     "iso": "CZE",
     "score": 22,
     "rank": 2
    },
    {
     "iso": "DEU",
     "score": 24,
     "rank": 2
    },
    {
     "iso": "DMA",
     "score": 41,
     "rank": 2
    },
    {
     "iso": "DNK",
     "score": 22,
     "rank": 1
    },
    {
     "iso": "DOM",
     "score": 43,
     "rank": 1
    },
    {
     "iso": "ECU",
     "score": 16,
     "rank": 1
    },
    {
     "iso": "EGY",
     "score": 10,
     "rank": 15
    },
    {
     "iso": "ESP",
     "score": 24,
     "rank": 1
    },
    {
     "iso": "EST",
     "score": 24,
     "rank": 1
    },
    {
     "iso": "ETH",
     "score": 13,
     "rank": 10
    },
    {
     "iso": "FIN",
     "score": 25,
     "rank": 1
    },
    {
     "iso": "FJI",
     "score": 32,
     "rank": 3
    },
    {
     "iso": "FRA",
     "score": 25,
     "rank": 1
    },
    {
     "iso": "GAB",
     "score": 8,
     "rank": 11
    },
    {
     "iso": "GBR",
     "score": 40,
     "rank": 2
    },
    {
     "iso": "GHA",
     "score": 11,
     "rank": 8
    },
    {
     "iso": "GIN",
     "score": 15,
     "rank": 13
    },
    {
     "iso": "GMB",
     "score": 12,
     "rank": 6
    },
    {
     "iso": "GRC",
     "score": 20,
     "rank": 1
    },
    {
     "iso": "GTM",
     "score": 8,
     "rank": 10
    },
    {
     "iso": "GUY",
     "score": 31,
     "rank": 3
    },
    {
     "iso": "HKG",
     "score": 37,
     "rank": 4
    },
    {
     "iso": "HND",
     "score": 10,
     "rank": 9
    },
    {
     "iso": "HRV",
     "score": 21,
     "rank": 3
    },
    {
     "iso": "HUN",
     "score": 39,
     "rank": 1
    },
    {
     "iso": "IDN",
     "score": 10,
     "rank": 13
    },
    {
     "iso": "IND",
     "score": 19,
     "rank": 7
    },
    {
     "iso": "IRL",
     "score": 24,
     "rank": 1
    },
    {
     "iso": "IRN",
     "score": 12,
     "rank": 7
    },
    {
     "iso": "IRQ",
     "score": 17,
     "rank": 7
    },
    {
     "iso": "ISL",
     "score": 24,
     "rank": 2
    },
    {
     "iso": "ISR",
     "score": 73,
     "rank": 1
    },
    {
     "iso": "ITA",
     "score": 22,
     "rank": 1
    },
    {
     "iso": "JAM",
     "score": 16,
     "rank": 7
    },
    {
     "iso": "JOR",
     "score": 18,
     "rank": 3
    },
    {
     "iso": "JPN",
     "score": 19,
     "rank": 3
    },
    {
     "iso": "KAZ",
     "score": 24,
     "rank": 3
    },
    {
     "iso": "KEN",
     "score": 7,
     "rank": 13
    },
    {
     "iso": "KHM",
     "score": 27,
     "rank": 1
    },
    {
     "iso": "KOR",
     "score": 27,
     "rank": 2
    },
    {
     "iso": "KWT",
     "score": 20,
     "rank": 4
    },
    {
     "iso": "LAO",
     "score": 24,
     "rank": 4
    },
    {
     "iso": "LBN",
     "score": 17,
     "rank": 7
    },
    {
     "iso": "LKA",
     "score": 15,
     "rank": 3
    },
    {
     "iso": "LSO",
     "score": 11,
     "rank": 9
    },
    {
     "iso": "LTU",
     "score": 22,
     "rank": 2
    },
    {
     "iso": "LUX",
     "score": 26,
     "rank": 1
    },
    {
     "iso": "LVA",
     "score": 10,
     "rank": 3
    },
    {
     "iso": "MAR",
     "score": 26,
     "rank": 2
    },
    {
     "iso": "MCO",
     "score": 42,
     "rank": 4
    },
    {
     "iso": "MDA",
     "score": 18,
     "rank": 15
    },
    {
     "iso": "MEX",
     "score": 12,
     "rank": 4
    },
    {
     "iso": "MLI",
     "score": 11,
     "rank": 8
    },
    {
     "iso": "MLT",
     "score": 56,
     "rank": 1
    },
    {
     "iso": "MMR",
     "score": 9,
     "rank": 13
    },
    {
     "iso": "MNG",
     "score": 66,
     "rank": 1
    },
    {
     "iso": "MOZ",
     "score": 11,
     "rank": 11
    },
    {
     "iso": "MRT",
     "score": 11,
     "rank": 13
    },
    {
     "iso": "MUS",
     "score": 13,
     "rank": 4
    },
    {
     "iso": "MWI",
     "score": 14,
     "rank": 7
    },
    {
     "iso": "MYS",
     "score": 22,
     "rank": 2
    },
    {
     "iso": "NAM",
     "score": 13,
     "rank": 8
    },
    {
     "iso": "NGA",
     "score": 11,
     "rank": 7
    },
    {
     "iso": "NLD",
     "score": 28,
     "rank": 1
    },
    {
     "iso": "NOR",
     "score": 22,
     "rank": 1
    },
    {
     "iso": "NPL",
     "score": 10,
     "rank": 11
    },
    {
     "iso": "NZL",
     "score": 18,
     "rank": 5
    },
    {
     "iso": "OMN",
     "score": 11,
     "rank": 7
    },
    {
     "iso": "PAK",
     "score": 13,
     "rank": 9
    },
    {
     "iso": "PAN",
     "score": 18,
     "rank": 4
    },
    {
     "iso": "PER",
     "score": 16,
     "rank": 8
    },
    {
     "iso": "PHL",
     "score": 14,
     "rank": 8
    },
    {
     "iso": "PNG",
     "score": 13,
     "rank": 8
    },
    {
     "iso": "POL",
     "score": 22,
     "rank": 2
    },
    {
     "iso": "PRT",
     "score": 24,
     "rank": 1
    },
    {
     "iso": "PRY",
     "score": 14,
     "rank": 4
    },
    {
     "iso": "QAT",
     "score": 34,
     "rank": 1
    },
    {
     "iso": "ROU",
     "score": 28,
     "rank": 3
    },
    {
     "iso": "RUS",
     "score": 18,
     "rank": 6
    },
    {
     "iso": "RWA",
     "score": 8,
     "rank": 11
    },
    {
     "iso": "SAU",
     "score": 29,
     "rank": 3
    },
    {
     "iso": "SDN",
     "score": 12,
     "rank": 7
    },
    {
     "iso": "SEN",
     "score": 14,
     "rank": 5
    },
    {
     "iso": "SGP",
     "score": 38,
     "rank": 4
    },
    {
     "iso": "SLE",
     "score": 13,
     "rank": 14
    },
    {
     "iso": "SLV",
     "score": 30,
     "rank": 12
    },
    {
     "iso": "SMR",
     "score": 76,
     "rank": 1
    },
    {
     "iso": "SOM",
     "score": 10,
     "rank": 8
    },
    {
     "iso": "SRB",
     "score": 38,
     "rank": 2
    },
    {
     "iso": "SSD",
     "score": 13,
     "rank": 8
    },
    {
     "iso": "SVK",
     "score": 28,
     "rank": 3
    },
    {
     "iso": "SVN",
     "score": 23,
     "rank": 2
    },
    {
     "iso": "SWE",
     "score": 21,
     "rank": 1
    },
    {
     "iso": "SWZ",
     "score": 18,
     "rank": 14
    },
    {
     "iso": "SYC",
     "score": 79,
     "rank": 1
    },
    {
     "iso": "SYR",
     "score": 5,
     "rank": 10
    },
    {
     "iso": "TGO",
     "score": 11,
     "rank": 6
    },
    {
     "iso": "THA",
     "score": 13,
     "rank": 5
    },
    {
     "iso": "TLS",
     "score": 30,
     "rank": 7
    },
    {
     "iso": "TTO",
     "score": 14,
     "rank": 4
    },
    {
     "iso": "TUN",
     "score": 18,
     "rank": 4
    },
    {
     "iso": "TUR",
     "score": 24,
     "rank": 1
    },
    {
     "iso": "TWN",
     "score": 20,
     "rank": 12
    },
    {
     "iso": "UGA",
     "score": 10,
     "rank": 8
    },
    {
     "iso": "UKR",
     "score": 13,
     "rank": 8
    },
    {
     "iso": "URY",
     "score": 68,
     "rank": 1
    },
    {
     "iso": "USA",
     "score": 39,
     "rank": 1
    },
    {
     "iso": "UZB",
     "score": 21,
     "rank": 14
    },
    {
     "iso": "VEN",
     "score": 4,
     "rank": 11
    },
    {
     "iso": "VNM",
     "score": 11,
     "rank": 9
    },
    {
     "iso": "ZAF",
     "score": 5,
     "rank": 6
    },
    {
     "iso": "ZMB",
     "score": 12,
     "rank": 9
    },
    {
     "iso": "ZWE",
     "score": 17,
     "rank": 10
    }
   ]
  },
  {
   "label": "Month 5",
   "data": [
    {
     "iso": "AFG",
     "score": 7,
     "rank": 6
    },
    {
     "iso": "AGO",
     "score": 12,
     "rank": 9
    },
    {
     "iso": "ALB",
     "score": 20,
     "rank": 4
    },
    {
     "iso": "AND",
     "score": 52,
     "rank": 2
    },
    {
     "iso": "ARE",
     "score": 80,
     "rank": 1
    },
    {
     "iso": "ARG",
     "score": 21,
     "rank": 4
    },
    {
     "iso": "AUS",
     "score": 32,
     "rank": 14
    },
    {
     "iso": "AUT",
     "score": 35,
     "rank": 2
    },
    {
     "iso": "AZE",
     "score": 29,
     "rank": 3
    },
    {
     "iso": "BEL",
     "score": 36,
     "rank": 1
    },
    {
     "iso": "BGD",
     "score": 8,
     "rank": 10
    },
    {
     "iso": "BGR",
     "score": 25,
     "rank": 8
    },
    {
     "iso": "BHR",
     "score": 53,
     "rank": 11
    },
    {
     "iso": "BHS",
     "score": 29,
     "rank": 5
    },
    {
     "iso": "BIH",
     "score": 16,
     "rank": 5
    },
    {
     "iso": "BLR",
     "score": 7,
     "rank": 7
    },
    {
     "iso": "BLZ",
     "score": 30,
     "rank": 11
    },
    {
     "iso": "BOL",
     "score": 15,
     "rank": 4
    },
    {
     "iso": "BRA",
     "score": 30,
     "rank": 2
    },
    {
     "iso": "BRB",
     "score": 41,
     "rank": 3
    },
    {
     "iso": "BRN",
     "score": 50,
     "rank": 3
    },
    {
     "iso": "BTN",
     "score": 80,
     "rank": 1
    },
    {
     "iso": "BWA",
     "score": 14,
     "rank": 8
    },
    {
     "iso": "CAN",
     "score": 31,
     "rank": 1
    },
    {
     "iso": "CHE",
     "score": 49,
     "rank": 1
    },
    {
     "iso": "CHL",
     "score": 54,
     "rank": 1
    },
    {
     "iso": "CHN",
     "score": 25,
     "rank": 3
    },
    {
     "iso": "CIV",
     "score": 17,
     "rank": 6
    },
    {
     "iso": "CPV",
     "score": 27,
     "rank": 8
    },
    {
     "iso": "CRI",
     "score": 24,
     "rank": 2
    },
    {
     "iso": "CYP",
     "score": 42,
     "rank": 1
    },
    {
     "iso": "CZE",
     "score": 32,
     "rank": 2
    },
    {
     "iso": "DEU",
     "score": 36,
     "rank": 2
    },
    {
     "iso": "DMA",
     "score": 43,
     "rank": 2
    },
    {
     "iso": "DNK",
     "score": 31,
     "rank": 1
    },
    {
     "iso": "DOM",
     "score": 56,
     "rank": 1
    },
    {
     "iso": "ECU",
     "score": 23,
     "rank": 1
    },
    {
     "iso": "EGY",
     "score": 12,
     "rank": 15
    },
    {
     "iso": "ESP",
     "score": 37,
     "rank": 1
    },
    {
     "iso": "EST",
     "score": 36,
     "rank": 1
    },
    {
     "iso": "FIN",
     "score": 35,
     "rank": 1
    },
    {
     "iso": "FJI",
     "score": 49,
     "rank": 3
    },
    {
     "iso": "FRA",
     "score": 39,
     "rank": 1
    },
    {
     "iso": "GAB",
     "score": 9,
     "rank": 11
    },
    {
     "iso": "GBR",
     "score": 51,
     "rank": 2
    },
    {
     "iso": "GHA",
     "score": 11,
     "rank": 8
    },
    {
     "iso": "GIN",
     "score": 16,
     "rank": 13
    },
    {
     "iso": "GMB",
     "score": 15,
     "rank": 6
    },
    {
     "iso": "GRC",
     "score": 36,
     "rank": 1
    },
    {
     "iso": "GTM",
     "score": 15,
     "rank": 10
    },
    {
     "iso": "GUY",
     "score": 34,
     "rank": 3
    },
    {
     "iso": "HKG",
     "score": 48,
     "rank": 4
    },
    {
     "iso": "HND",
     "score": 19,
     "rank": 9
    },
    {
     "iso": "HRV",
     "score": 33,
     "rank": 3
    },
    {
     "iso": "HUN",
     "score": 58,
     "rank": 1
    },
    {
     "iso": "IDN",
     "score": 11,
     "rank": 13
    },
    {
     "iso": "IND",
     "score": 21,
     "rank": 7
    },
    {
     "iso": "IRL",
     "score": 32,
     "rank": 1
    },
    {
     "iso": "IRN",
     "score": 12,
     "rank": 7
    },
    {
     "iso": "IRQ",
     "score": 17,
     "rank": 7
    },
    {
     "iso": "ISL",
     "score": 49,
     "rank": 2
    },
    {
     "iso": "ISR",
     "score": 74,
     "rank": 1
    },
    {
     "iso": "ITA",
     "score": 36,
     "rank": 1
    },
    {
     "iso": "JAM",
     "score": 18,
     "rank": 7
    },
    {
     "iso": "JOR",
     "score": 24,
     "rank": 3
    },
    {
     "iso": "JPN",
     "score": 39,
     "rank": 3
    },
    {
     "iso": "KAZ",
     "score": 29,
     "rank": 3
    },
    {
     "iso": "KEN",
     "score": 7,
     "rank": 13
    },
    {
     "iso": "KHM",
     "score": 37,
     "rank": 1
    },
    {
     "iso": "KOR",
     "score": 31,
     "rank": 2
    },
    {
     "iso": "KWT",
     "score": 31,
     "rank": 4
    },
    {
     "iso": "LAO",
     "score": 26,
     "rank": 4
    },
    {
     "iso": "LBN",
     "score": 24,
     "rank": 7
    },
    {
     "iso": "LKA",
     "score": 20,
     "rank": 3
    },
    {
     "iso": "LSO",
     "score": 5,
     "rank": 9
    },
    {
     "iso": "LTU",
     "score": 34,
     "rank": 2
    },
    {
     "iso": "LUX",
     "score": 41,
     "rank": 1
    },
    {
     "iso": "LVA",
     "score": 16,
     "rank": 3
    },
    {
     "iso": "MAR",
     "score": 31,
     "rank": 2
    },
    {
     "iso": "MCO",
     "score": 49,
     "rank": 4
    },
    {
     "iso": "MDA",
     "score": 22,
     "rank": 15
    },
    {
     "iso": "MEX",
     "score": 18,
     "rank": 4
    },
    {
     "iso": "MLI",
     "score": 11,
     "rank": 8
    },
    {
     "iso": "MLT",
     "score": 77,
     "rank": 1
    },
    {
     "iso": "MMR",
     "score": 9,
     "rank": 13
    },
    {
     "iso": "MNG",
     "score": 71,
     "rank": 1
    },
    {
     "iso": "MOZ",
     "score": 10,
     "rank": 11
    },
    {
     "iso": "MRT",
     "score": 12,
     "rank": 13
    },
    {
     "iso": "MUS",
     "score": 36,
     "rank": 4
    },
    {
     "iso": "MWI",
     "score": 17,
     "rank": 7
    },
    {
     "iso": "NAM",
     "score": 14,
     "rank": 8
    },
    {
     "iso": "NER",
     "score": 9,
     "rank": 1
    },
    {
     "iso": "NGA",
     "score": 13,
     "rank": 7
    },
    {
     "iso": "NIC",
     "score": 12,
     "rank": 5
    },
    {
     "iso": "NLD",
     "score": 40,
     "rank": 1
    },
    {
     "iso": "NOR",
     "score": 29,
     "rank": 1
    },
    {
     "iso": "NPL",
     "score": 11,
     "rank": 11
    },
    {
     "iso": "NZL",
     "score": 24,
     "rank": 5
    },
    {
     "iso": "OMN",
     "score": 11,
     "rank": 7
    },
    {
     "iso": "PAN",
     "score": 28,
     "rank": 4
    },
    {
     "iso": "PER",
     "score": 23,
     "rank": 8
    },
    {
     "iso": "PHL",
     "score": 17,
     "rank": 8
    },
    {
     "iso": "PNG",
     "score": 16,
     "rank": 8
    },
    {
     "iso": "POL",
     "score": 39,
     "rank": 2
    },
    {
     "iso": "PRT",
     "score": 38,
     "rank": 1
    },
    {
     "iso": "PRY",
     "score": 23,
     "rank": 4
    },
    {
     "iso": "QAT",
     "score": 50,
     "rank": 1
    },
    {
     "iso": "ROU",
     "score": 34,
     "rank": 3
    },
    {
     "iso": "RUS",
     "score": 23,
     "rank": 6
    },
    {
     "iso": "RWA",
     "score": 8,
     "rank": 11
    },
    {
     "iso": "SAU",
     "score": 36,
     "rank": 3
    },
    {
     "iso": "SDN",
     "score": 13,
     "rank": 7
    },
    {
     "iso": "SEN",
     "score": 15,
     "rank": 5
    },
    {
     "iso": "SGP",
     "score": 49,
     "rank": 4
    },
    {
     "iso": "SLV",
     "score": 39,
     "rank": 12
    },
    {
     "iso": "SMR",
     "score": 78,
     "rank": 1
    },
    {
     "iso": "SRB",
     "score": 46,
     "rank": 2
    },
    {
     "iso": "SVK",
     "score": 40,
     "rank": 3
    },
    {
     "iso": "SVN",
     "score": 32,
     "rank": 2
    },
    {
     "iso": "SWE",
     "score": 32,
     "rank": 1
    },
    {
     "iso": "SWZ",
     "score": 21,
     "rank": 14
    },
    {
     "iso": "SYC",
     "score": 83,
     "rank": 1
    },
    {
     "iso": "SYR",
     "score": 6,
     "rank": 10
    },
    {
     "iso": "TGO",
     "score": 12,
     "rank": 6
    },
    {
     "iso": "THA",
     "score": 17,
     "rank": 5
    },
    {
     "iso": "TTO",
     "score": 22,
     "rank": 4
    },
    {
     "iso": "TUN",
     "score": 23,
     "rank": 4
    },
    {
     "iso": "TUR",
     "score": 28,
     "rank": 1
    },
    {
     "iso": "TWN",
     "score": 29,
     "rank": 12
    },
    {
     "iso": "UGA",
     "score": 10,
     "rank": 8
    },
    {
     "iso": "UKR",
     "score": 18,
     "rank": 8
    },
    {
     "iso": "URY",
     "score": 81,
     "rank": 1
    },
    {
     "iso": "USA",
     "score": 54,
     "rank": 1
    },
    {
     "iso": "UZB",
     "score": 33,
     "rank": 14
    },
    {
     "iso": "VEN",
     "score": 10,
     "rank": 11
    },
    {
     "iso": "VNM",
     "score": 13,
     "rank": 9
    },
    {
     "iso": "ZAF",
     "score": 13,
     "rank": 6
    },
    {
     "iso": "ZWE",
     "score": 20,
     "rank": 10
    }
   ]
  },
  {
   "label": "Month 6",
   "data": [
    {
     "iso": "AGO",
     "score": 18,
     "rank": 9
    },
    {
     "iso": "ALB",
     "score": 23,
     "rank": 4
    },
    {
     "iso": "AND",
     "score": 65,
     "rank": 2
    },
    {
     "iso": "ARE",
     "score": 91,
     "rank": 1
    },
    {
     "iso": "ARG",
     "score": 31,
     "rank": 4
    },
    {
     "iso": "AUS",
     "score": 44,
     "rank": 14
    },
    {
     "iso": "AUT",
     "score": 51,
     "rank": 2
    },
    {
     "iso": "AZE",
     "score": 36,
     "rank": 3
    },
    {
     "iso": "BEL",
     "score": 57,
     "rank": 1
    },
    {
     "iso": "BGD",
     "score": 9,
     "rank": 10
    },
    {
     "iso": "BGR",
     "score": 28,
     "rank": 8
    },
    {
     "iso": "BHR",
     "score": 67,
     "rank": 11
    },
    {
     "iso": "BIH",
     "score": 21,
     "rank": 5
    },
    {
     "iso": "BLR",
     "score": 15,
     "rank": 7
    },
    {
     "iso": "BLZ",
     "score": 36,
     "rank": 11
    },
    {
     "iso": "BOL",
     "score": 27,
     "rank": 4
    },
    {
     "iso": "BRA",
     "score": 40,
     "rank": 2
    },
    {
     "iso": "BRB",
     "score": 44,
     "rank": 3
    },
    {
     "iso": "CAN",
     "score": 50,
     "rank": 1
    },
    {
     "iso": "CHE",
     "score": 61,
     "rank": 1
    },
    {
     "iso": "CHL",
     "score": 67,
     "rank": 1
    },
    {
     "iso": "CHN",
     "score": 42,
     "rank": 3
    },
    {
     "iso": "CIV",
     "score": 18,
     "rank": 6
    },
    {
     "iso": "COL",
     "score": 44,
     "rank": 14
    },
    {
     "iso": "CRI",
     "score": 33,
     "rank": 2
    },
    {
     "iso": "CYP",
     "score": 54,
     "rank": 1
    },
    {
     "iso": "CZE",
     "score": 47,
     "rank": 2
    },
    {
     "iso": "DEU",
     "score": 54,
     "rank": 2
    },
    {
     "iso": "DMA",
     "score": 43,
     "rank": 2
    },
    {
     "iso": "DNK",
     "score": 46,
     "rank": 1
    },
    {
     "iso": "DOM",
     "score": 63,
     "rank": 1
    },
    {
     "iso": "ECU",
     "score": 38,
     "rank": 1
    },
    {
     "iso": "EGY",
     "score": 12,
     "rank": 15
    },
    {
     "iso": "ESP",
     "score": 54,
     "rank": 1
    },
    {
     "iso": "EST",
     "score": 49,
     "rank": 1
    },
    {
     "iso": "FIN",
     "score": 49,
     "rank": 1
    },
    {
     "iso": "FRA",
     "score": 53,
     "rank": 1
    },
    {
     "iso": "GBR",
     "score": 62,
     "rank": 2
    },
    {
     "iso": "GRC",
     "score": 48,
     "rank": 1
    },
    {
     "iso": "GTM",
     "score": 23,
     "rank": 10
    },
    {
     "iso": "GUY",
     "score": 38,
     "rank": 3
    },
    {
     "iso": "HKG",
     "score": 60,
     "rank": 4
    },
    {
     "iso": "HND",
     "score": 31,
     "rank": 9
    },
    {
     "iso": "HRV",
     "score": 41,
     "rank": 3
    },
    {
     "iso": "HUN",
     "score": 62,
     "rank": 1
    },
    {
     "iso": "IDN",
     "score": 15,
     "rank": 13
    },
    {
     "iso": "IND",
     "score": 26,
     "rank": 7
    },
    {
     "iso": "IRL",
     "score": 49,
     "rank": 1
    },
    {
     "iso": "IRN",
     "score": 16,
     "rank": 7
    },
    {
     "iso": "ISL",
     "score": 70,
     "rank": 2
    },
    {
     "iso": "ISR",
     "score": 75,
     "rank": 1
    },
    {
     "iso": "ITA",
     "score": 52,
     "rank": 1
    },
    {
     "iso": "JOR",
     "score": 33,
     "rank": 3
    },
    {
     "iso": "JPN",
     "score": 55,
     "rank": 3
    },
    {
     "iso": "KAZ",
     "score": 39,
     "rank": 3
    },
    {
     "iso": "KEN",
     "score": 12,
     "rank": 13
    },
    {
     "iso": "KHM",
     "score": 53,
     "rank": 1
    },
    {
     "iso": "KOR",
     "score": 51,
     "rank": 2
    },
    {
     "iso": "LBN",
     "score": 28,
     "rank": 7
    },
    {
     "iso": "LKA",
     "score": 38,
     "rank": 3
    },
    {
     "iso": "LTU",
     "score": 51,
     "rank": 2
    },
    {
     "iso": "LUX",
     "score": 56,
     "rank": 1
    },
    {
     "iso": "LVA",
     "score": 36,
     "rank": 3
    },
    {
     "iso": "MAR",
     "score": 38,
     "rank": 2
    },
    {
     "iso": "MCO",
     "score": 61,
     "rank": 4
    },
    {
     "iso": "MDA",
     "score": 25,
     "rank": 15
    },
    {
     "iso": "MEX",
     "score": 24,
     "rank": 4
    },
    {
     "iso": "MLT",
     "score": 89,
     "rank": 1
    },
    {
     "iso": "MMR",
     "score": 10,
     "rank": 13
    },
    {
     "iso": "MNG",
     "score": 75,
     "rank": 1
    },
    {
     "iso": "MUS",
     "score": 54,
     "rank": 4
    },
    {
     "iso": "NGA",
     "score": 12,
     "rank": 7
    },
    {
     "iso": "NIC",
     "score": 14,
     "rank": 5
    },
    {
     "iso": "NLD",
     "score": 61,
     "rank": 1
    },
    {
     "iso": "NOR",
     "score": 42,
     "rank": 1
    },
    {
     "iso": "NPL",
     "score": 21,
     "rank": 11
    },
    {
     "iso": "NZL",
     "score": 38,
     "rank": 5
    },
    {
     "iso": "OMN",
     "score": 20,
     "rank": 7
    },
    {
     "iso": "PAK",
     "score": 19,
     "rank": 9
    },
    {
     "iso": "PAN",
     "score": 33,
     "rank": 4
    },
    {
     "iso": "PER",
     "score": 34,
     "rank": 8
    },
    {
     "iso": "PHL",
     "score": 23,
     "rank": 8
    },
    {
     "iso": "POL",
     "score": 51,
     "rank": 2
    },
    {
     "iso": "PRT",
     "score": 50,
     "rank": 1
    },
    {
     "iso": "PRY",
     "score": 35,
     "rank": 4
    },
    {
     "iso": "QAT",
     "score": 61,
     "rank": 1
    },
    {
     "iso": "ROU",
     "score": 38,
     "rank": 3
    },
    {
     "iso": "RUS",
     "score": 26,
     "rank": 6
    },
    {
     "iso": "RWA",
     "score": 10,
     "rank": 11
    },
    {
     "iso": "SAU",
     "score": 41,
     "rank": 3
    },
    {
     "iso": "SEN",
     "score": 17,
     "rank": 5
    },
    {
     "iso": "SGP",
     "score": 66,
     "rank": 4
    },
    {
     "iso": "SLV",
     "score": 51,
     "rank": 12
    },
    {
     "iso": "SMR",
     "score": 82,
     "rank": 1
    },
    {
     "iso": "SRB",
     "score": 49,
     "rank": 2
    },
    {
     "iso": "SVK",
     "score": 49,
     "rank": 3
    },
    {
     "iso": "SVN",
     "score": 45,
     "rank": 2
    },
    {
     "iso": "SWE",
     "score": 47,
     "rank": 1
    },
    {
     "iso": "SYC",
     "score": 84,
     "rank": 1
    },
    {
     "iso": "SYR",
     "score": 11,
     "rank": 10
    },
    {
     "iso": "THA",
     "score": 34,
     "rank": 5
    },
    {
     "iso": "TTO",
     "score": 35,
     "rank": 4
    },
    {
     "iso": "TUR",
     "score": 43,
     "rank": 1
    },
    {
     "iso": "UKR",
     "score": 22,
     "rank": 8
    },
    {
     "iso": "URY",
     "score": 91,
     "rank": 1
    },
    {
     "iso": "USA",
     "score": 61,
     "rank": 1
    },
    {
     "iso": "ZAF",
     "score": 18,
     "rank": 6
    },
    {
     "iso": "ZWE",
     "score": 27,
     "rank": 10
    }
   ]
  },
  {
   "label": "Month 7",
   "data": [
    {
     "iso": "ALB",
     "score": 32,
     "rank": 4
    },
    {
     "iso": "AND",
     "score": 73,
     "rank": 2
    },
    {
     "iso": "ARE",
     "score": 98,
     "rank": 1
    },
    {
     "iso": "ARG",
     "score": 41,
     "rank": 4
    },
    {
     "iso": "AUT",
     "score": 65,
     "rank": 2
    },
    {
     "iso": "AZE",
     "score": 43,
     "rank": 3
    },
    {
     "iso": "BEL",
     "score": 74,
     "rank": 1
    },
    {
     "iso": "BGD",
     "score": 16,
     "rank": 10
    },
    {
     "iso": "BGR",
     "score": 29,
     "rank": 8
    },
    {
     "iso": "BHR",
     "score": 76,
     "rank": 11
    },
    {
     "iso": "BLR",
     "score": 18,
     "rank": 7
    },
    {
     "iso": "BOL",
     "score": 36,
     "rank": 4
    },
    {
     "iso": "BRA",
     "score": 50,
     "rank": 2
    },
    {
     "iso": "CAN",
     "score": 71,
     "rank": 1
    },
    {
     "iso": "CHE",
     "score": 68,
     "rank": 1
    },
    {
     "iso": "CHL",
     "score": 76,
     "rank": 1
    },
    {
     "iso": "CHN",
     "score": 61,
     "rank": 3
    },
    {
     "iso": "CRI",
     "score": 39,
     "rank": 2
    },
    {
     "iso": "CYP",
     "score": 63,
     "rank": 1
    },
    {
     "iso": "CZE",
     "score": 60,
     "rank": 2
    },
    {
     "iso": "DEU",
     "score": 68,
     "rank": 2
    },
    {
     "iso": "DNK",
     "score": 66,
     "rank": 1
    },
    {
     "iso": "DZA",
     "score": 14,
     "rank": 9
    },
    {
     "iso": "ECU",
     "score": 56,
     "rank": 1
    },
    {
     "iso": "EGY",
     "score": 12,
     "rank": 15
    },
    {
     "iso": "ESP",
     "score": 71,
     "rank": 1
    },
    {
     "iso": "EST",
     "score": 56,
     "rank": 1
    },
    {
     "iso": "FIN",
     "score": 63,
     "rank": 1
    },
    {
     "iso": "FRA",
     "score": 67,
     "rank": 1
    },
    {
     "iso": "GBR",
     "score": 72,
     "rank": 2
    },
    {
     "iso": "GRC",
     "score": 60,
     "rank": 1
    },
    {
     "iso": "HRV",
     "score": 48,
     "rank": 3
    },
    {
     "iso": "IDN",
     "score": 21,
     "rank": 13
    },
    {
     "iso": "IND",
     "score": 31,
     "rank": 7
    },
    {
     "iso": "IRL",
     "score": 68,
     "rank": 1
    },
    {
     "iso": "ISL",
     "score": 82,
     "rank": 2
    },
    {
     "iso": "ISR",
     "score": 77,
     "rank": 1
    },
    {
     "iso": "ITA",
     "score": 68,
     "rank": 1
    },
    {
     "iso": "JOR",
     "score": 39,
     "rank": 3
    },
    {
     "iso": "KAZ",
     "score": 46,
     "rank": 3
    },
    {
     "iso": "KWT",
     "score": 40,
     "rank": 4
    },
    {
     "iso": "LKA",
     "score": 56,
     "rank": 3
    },
    {
     "iso": "LTU",
     "score": 61,
     "rank": 2
    },
    {
     "iso": "LUX",
     "score": 69,
     "rank": 1
    },
    {
     "iso": "LVA",
     "score": 45,
     "rank": 3
    },
    {
     "iso": "MCO",
     "score": 66,
     "rank": 4
    },
    {
     "iso": "MEX",
     "score": 31,
     "rank": 4
    },
    {
     "iso": "MLT",
     "score": 96,
     "rank": 1
    },
    {
     "iso": "MMR",
     "score": 18,
     "rank": 13
    },
    {
     "iso": "MUS",
     "score": 68,
     "rank": 4
    },
    {
     "iso": "NLD",
     "score": 73,
     "rank": 1
    },
    {
     "iso": "NOR",
     "score": 56,
     "rank": 1
    },
    {
     "iso": "NPL",
     "score": 27,
     "rank": 11
    },
    {
     "iso": "OMN",
     "score": 30,
     "rank": 7
    },
    {
     "iso": "PAK",
     "score": 28,
     "rank": 9
    },
    {
     "iso": "PAN",
     "score": 52,
     "rank": 4
    },
    {
     "iso": "POL",
     "score": 59,
     "rank": 2
    },
    {
     "iso": "PRT",
     "score": 68,
     "rank": 1
    },
    {
     "iso": "QAT",
     "score": 72,
     "rank": 1
    },
    {
     "iso": "ROU",
     "score": 39,
     "rank": 3
    },
    {
     "iso": "RUS",
     "score": 31,
     "rank": 6
    },
    {
     "iso": "SAU",
     "score": 55,
     "rank": 3
    },
    {
     "iso": "SGP",
     "score": 83,
     "rank": 4
    },
    {
     "iso": "SRB",
     "score": 51,
     "rank": 2
    },
    {
     "iso": "SVK",
     "score": 54,
     "rank": 3
    },
    {
     "iso": "SVN",
     "score": 52,
     "rank": 2
    },
    {
     "iso": "SWE",
     "score": 61,
     "rank": 1
    },
    {
     "iso": "SYC",
     "score": 85,
     "rank": 1
    },
    {
     "iso": "TUR",
     "score": 55,
     "rank": 1
    },
    {
     "iso": "USA",
     "score": 65,
     "rank": 1
    }
   ]
  },
  {
   "label": "Month 8",
   "data": [
    {
     "iso": "ARG",
     "score": 54,
     "rank": 4
    },
    {
     "iso": "AUT",
     "score": 71,
     "rank": 2
    },
    {
     "iso": "BEL",
     "score": 82,
     "rank": 1
    },
    {
     "iso": "BGR",
     "score": 31,
     "rank": 8
    },
    {
     "iso": "BHR",
     "score": 81,
     "rank": 11
    },
    {
     "iso": "BLR",
     "score": 20,
     "rank": 7
    },
    {
     "iso": "CAN",
     "score": 81,
     "rank": 1
    },
    {
     "iso": "CHL",
     "score": 83,
     "rank": 1
    },
    {
     "iso": "CHN",
     "score": 77,
     "rank": 3
    },
    {
     "iso": "CRI",
     "score": 49,
     "rank": 2
    },
    {
     "iso": "CZE",
     "score": 67,
     "rank": 2
    },
    {
     "iso": "DEU",
     "score": 74,
     "rank": 2
    },
    {
     "iso": "DNK",
     "score": 83,
     "rank": 1
    },
    {
     "iso": "ESP",
     "score": 84,
     "rank": 1
    },
    {
     "iso": "EST",
     "score": 61,
     "rank": 1
    },
    {
     "iso": "FIN",
     "score": 75,
     "rank": 1
    },
    {
     "iso": "FRA",
     "score": 77,
     "rank": 1
    },
    {
     "iso": "GBR",
     "score": 77,
     "rank": 2
    },
    {
     "iso": "GRC",
     "score": 65,
     "rank": 1
    },
    {
     "iso": "HRV",
     "score": 51,
     "rank": 3
    },
    {
     "iso": "IRL",
     "score": 79,
     "rank": 1
    },
    {
     "iso": "ISL",
     "score": 90,
     "rank": 2
    },
    {
     "iso": "ISR",
     "score": 84,
     "rank": 1
    },
    {
     "iso": "ITA",
     "score": 76,
     "rank": 1
    },
    {
     "iso": "LTU",
     "score": 71,
     "rank": 2
    },
    {
     "iso": "LUX",
     "score": 74,
     "rank": 1
    },
    {
     "iso": "LVA",
     "score": 50,
     "rank": 3
    },
    {
     "iso": "MCO",
     "score": 75,
     "rank": 4
    },
    {
     "iso": "MEX",
     "score": 46,
     "rank": 4
    },
    {
     "iso": "NOR",
     "score": 67,
     "rank": 1
    },
    {
     "iso": "OMN",
     "score": 44,
     "rank": 7
    },
    {
     "iso": "POL",
     "score": 62,
     "rank": 2
    },
    {
     "iso": "PRT",
     "score": 81,
     "rank": 1
    },
    {
     "iso": "QAT",
     "score": 83,
     "rank": 1
    },
    {
     "iso": "ROU",
     "score": 40,
     "rank": 3
    },
    {
     "iso": "RUS",
     "score": 38,
     "rank": 6
    },
    {
     "iso": "SWE",
     "score": 74,
     "rank": 1
    },
    {
     "iso": "USA",
     "score": 68,
     "rank": 1
    }
   ]
  },
  {
   "label": "Month 9",
   "data": [
    {
     "iso": "LVA",
     "score": 54,
     "rank": 3
    }
   ]
  },
  {
   "label": "Month 10",
   "data": []
  },
  {
   "label": "Month 11",
   "data": []
  },
  {
   "label": "Month 12",
   "data": []
  },
  {
   "label": "Month 13",
   "data": []
  },
  {
   "label": "Month 14",
   "data": []
  },
  {
   "label": "Month 15",
   "data": []
  },
  {
   "label": "Month 16",
   "data": []
  },
  {
   "label": "Month 17",
   "data": []
  },
  {
   "label": "Month 18",
   "data": []
  }
 ]
}